import android.database.sqlite.SQLiteDatabase;

public class bv extends bt
{
  static String a(String paramString1, String paramString2)
  {
    StringBuilder localStringBuilder1 = new StringBuilder();
    StringBuilder localStringBuilder2 = localStringBuilder1.append("update ").append(paramString1).append(" set ").append(paramString2).append(" = (0 - ").append(paramString2).append(")");
    return localStringBuilder1.toString();
  }

  static String a(String paramString1, String paramString2, String paramString3)
  {
    StringBuilder localStringBuilder1 = new StringBuilder();
    StringBuilder localStringBuilder2 = localStringBuilder1.append("(select serverId from t_local_server_id_map where ownerTable = '").append(paramString3).append("' and localId = ").append(paramString2).append(" and serverId > 0 )");
    StringBuilder localStringBuilder3 = new StringBuilder();
    StringBuilder localStringBuilder4 = localStringBuilder3.append("update ").append(paramString1).append(" set ").append(paramString2).append(" = ");
    StringBuilder localStringBuilder5 = localStringBuilder3.append("(");
    StringBuilder localStringBuilder6 = localStringBuilder3.append("    CASE");
    StringBuilder localStringBuilder7 = localStringBuilder3.append("        WHEN EXISTS ").append(localStringBuilder1);
    StringBuilder localStringBuilder8 = localStringBuilder3.append("            then ").append(localStringBuilder1);
    StringBuilder localStringBuilder9 = localStringBuilder3.append("        ELSE (").append(paramString2).append(")");
    StringBuilder localStringBuilder10 = localStringBuilder3.append("    END");
    StringBuilder localStringBuilder11 = localStringBuilder3.append(")");
    return localStringBuilder3.toString();
  }

  public static boolean b(SQLiteDatabase paramSQLiteDatabase)
  {
    bv localbv = new bv();
    localbv.a(paramSQLiteDatabase);
    return localbv.a();
  }

  // ERROR //
  public boolean a()
  {
    // Byte code:
    //   0: ldc 64
    //   2: ldc 66
    //   4: invokestatic 71	gj:a	(Ljava/lang/String;Ljava/lang/String;)V
    //   7: new 73	java/util/ArrayList
    //   10: dup
    //   11: bipush 50
    //   13: invokespecial 76	java/util/ArrayList:<init>	(I)V
    //   16: astore_1
    //   17: aload_1
    //   18: ldc 78
    //   20: invokeinterface 84 2 0
    //   25: istore_2
    //   26: aload_1
    //   27: ldc 86
    //   29: invokeinterface 84 2 0
    //   34: istore_3
    //   35: aload_1
    //   36: ldc 88
    //   38: invokeinterface 84 2 0
    //   43: istore 4
    //   45: aload_1
    //   46: ldc 90
    //   48: invokeinterface 84 2 0
    //   53: istore 5
    //   55: aload_1
    //   56: ldc 92
    //   58: invokeinterface 84 2 0
    //   63: istore 6
    //   65: aload_1
    //   66: ldc 94
    //   68: invokeinterface 84 2 0
    //   73: istore 7
    //   75: aload_1
    //   76: ldc 96
    //   78: invokeinterface 84 2 0
    //   83: istore 8
    //   85: iconst_0
    //   86: istore 9
    //   88: aconst_null
    //   89: astore 10
    //   91: aload_0
    //   92: getfield 99	bv:a	Landroid/database/sqlite/SQLiteDatabase;
    //   95: ldc 101
    //   97: aconst_null
    //   98: invokevirtual 107	android/database/sqlite/SQLiteDatabase:rawQuery	(Ljava/lang/String;[Ljava/lang/String;)Landroid/database/Cursor;
    //   101: astore 11
    //   103: aload 11
    //   105: astore 10
    //   107: aload 10
    //   109: invokeinterface 112 1 0
    //   114: ifeq +33 -> 147
    //   117: aload 10
    //   119: ldc 114
    //   121: invokeinterface 118 2 0
    //   126: istore 12
    //   128: aload 10
    //   130: iload 12
    //   132: invokeinterface 122 2 0
    //   137: istore 11
    //   139: iload 11
    //   141: ifle +6 -> 147
    //   144: iconst_1
    //   145: istore 9
    //   147: aload 10
    //   149: invokeinterface 125 1 0
    //   154: ldc 127
    //   156: astore 13
    //   158: iload 9
    //   160: ifeq +13 -> 173
    //   163: aload_1
    //   164: ldc 129
    //   166: invokeinterface 84 2 0
    //   171: istore 14
    //   173: aload_1
    //   174: aload 13
    //   176: invokeinterface 84 2 0
    //   181: istore 15
    //   183: aload_1
    //   184: ldc 131
    //   186: invokeinterface 84 2 0
    //   191: istore 16
    //   193: aload_1
    //   194: ldc 133
    //   196: invokeinterface 84 2 0
    //   201: istore 17
    //   203: ldc 135
    //   205: ldc 137
    //   207: invokestatic 139	bv:a	(Ljava/lang/String;Ljava/lang/String;)Ljava/lang/String;
    //   210: astore 18
    //   212: aload_1
    //   213: aload 18
    //   215: invokeinterface 84 2 0
    //   220: istore 19
    //   222: ldc 141
    //   224: ldc 143
    //   226: invokestatic 139	bv:a	(Ljava/lang/String;Ljava/lang/String;)Ljava/lang/String;
    //   229: astore 20
    //   231: aload_1
    //   232: aload 20
    //   234: invokeinterface 84 2 0
    //   239: istore 21
    //   241: ldc 141
    //   243: ldc 143
    //   245: ldc 141
    //   247: invokestatic 145	bv:a	(Ljava/lang/String;Ljava/lang/String;Ljava/lang/String;)Ljava/lang/String;
    //   250: astore 22
    //   252: aload_1
    //   253: aload 22
    //   255: invokeinterface 84 2 0
    //   260: istore 23
    //   262: ldc 147
    //   264: ldc 149
    //   266: invokestatic 139	bv:a	(Ljava/lang/String;Ljava/lang/String;)Ljava/lang/String;
    //   269: astore 24
    //   271: aload_1
    //   272: aload 24
    //   274: invokeinterface 84 2 0
    //   279: istore 25
    //   281: ldc 147
    //   283: ldc 149
    //   285: ldc 141
    //   287: invokestatic 145	bv:a	(Ljava/lang/String;Ljava/lang/String;Ljava/lang/String;)Ljava/lang/String;
    //   290: astore 26
    //   292: aload_1
    //   293: aload 26
    //   295: invokeinterface 84 2 0
    //   300: istore 27
    //   302: ldc 147
    //   304: ldc 151
    //   306: invokestatic 139	bv:a	(Ljava/lang/String;Ljava/lang/String;)Ljava/lang/String;
    //   309: astore 28
    //   311: aload_1
    //   312: aload 28
    //   314: invokeinterface 84 2 0
    //   319: istore 29
    //   321: ldc 147
    //   323: ldc 151
    //   325: ldc 141
    //   327: invokestatic 145	bv:a	(Ljava/lang/String;Ljava/lang/String;Ljava/lang/String;)Ljava/lang/String;
    //   330: astore 30
    //   332: aload_1
    //   333: aload 30
    //   335: invokeinterface 84 2 0
    //   340: istore 31
    //   342: ldc 153
    //   344: ldc 155
    //   346: invokestatic 139	bv:a	(Ljava/lang/String;Ljava/lang/String;)Ljava/lang/String;
    //   349: astore 32
    //   351: aload_1
    //   352: aload 32
    //   354: invokeinterface 84 2 0
    //   359: istore 33
    //   361: ldc 153
    //   363: ldc 155
    //   365: ldc 141
    //   367: invokestatic 145	bv:a	(Ljava/lang/String;Ljava/lang/String;Ljava/lang/String;)Ljava/lang/String;
    //   370: astore 34
    //   372: aload_1
    //   373: aload 34
    //   375: invokeinterface 84 2 0
    //   380: istore 35
    //   382: ldc 157
    //   384: ldc 143
    //   386: invokestatic 139	bv:a	(Ljava/lang/String;Ljava/lang/String;)Ljava/lang/String;
    //   389: astore 36
    //   391: aload_1
    //   392: aload 36
    //   394: invokeinterface 84 2 0
    //   399: istore 37
    //   401: ldc 157
    //   403: ldc 143
    //   405: ldc 141
    //   407: invokestatic 145	bv:a	(Ljava/lang/String;Ljava/lang/String;Ljava/lang/String;)Ljava/lang/String;
    //   410: astore 38
    //   412: aload_1
    //   413: aload 38
    //   415: invokeinterface 84 2 0
    //   420: istore 39
    //   422: ldc 159
    //   424: ldc 149
    //   426: invokestatic 139	bv:a	(Ljava/lang/String;Ljava/lang/String;)Ljava/lang/String;
    //   429: astore 40
    //   431: aload_1
    //   432: aload 40
    //   434: invokeinterface 84 2 0
    //   439: istore 41
    //   441: ldc 159
    //   443: ldc 149
    //   445: ldc 141
    //   447: invokestatic 145	bv:a	(Ljava/lang/String;Ljava/lang/String;Ljava/lang/String;)Ljava/lang/String;
    //   450: astore 42
    //   452: aload_1
    //   453: aload 42
    //   455: invokeinterface 84 2 0
    //   460: istore 43
    //   462: ldc 159
    //   464: ldc 151
    //   466: invokestatic 139	bv:a	(Ljava/lang/String;Ljava/lang/String;)Ljava/lang/String;
    //   469: astore 44
    //   471: aload_1
    //   472: aload 44
    //   474: invokeinterface 84 2 0
    //   479: istore 45
    //   481: ldc 159
    //   483: ldc 151
    //   485: ldc 141
    //   487: invokestatic 145	bv:a	(Ljava/lang/String;Ljava/lang/String;Ljava/lang/String;)Ljava/lang/String;
    //   490: astore 46
    //   492: aload_1
    //   493: aload 46
    //   495: invokeinterface 84 2 0
    //   500: istore 47
    //   502: ldc 161
    //   504: ldc 163
    //   506: invokestatic 139	bv:a	(Ljava/lang/String;Ljava/lang/String;)Ljava/lang/String;
    //   509: astore 48
    //   511: aload_1
    //   512: aload 48
    //   514: invokeinterface 84 2 0
    //   519: istore 49
    //   521: ldc 161
    //   523: ldc 163
    //   525: ldc 161
    //   527: invokestatic 145	bv:a	(Ljava/lang/String;Ljava/lang/String;Ljava/lang/String;)Ljava/lang/String;
    //   530: astore 50
    //   532: aload_1
    //   533: aload 50
    //   535: invokeinterface 84 2 0
    //   540: istore 51
    //   542: ldc 161
    //   544: ldc 165
    //   546: invokestatic 139	bv:a	(Ljava/lang/String;Ljava/lang/String;)Ljava/lang/String;
    //   549: astore 52
    //   551: aload_1
    //   552: aload 52
    //   554: invokeinterface 84 2 0
    //   559: istore 53
    //   561: ldc 161
    //   563: ldc 165
    //   565: ldc 161
    //   567: invokestatic 145	bv:a	(Ljava/lang/String;Ljava/lang/String;Ljava/lang/String;)Ljava/lang/String;
    //   570: astore 54
    //   572: aload_1
    //   573: aload 54
    //   575: invokeinterface 84 2 0
    //   580: istore 55
    //   582: aload_1
    //   583: ldc 167
    //   585: invokeinterface 84 2 0
    //   590: istore 56
    //   592: aload_1
    //   593: ldc 169
    //   595: invokeinterface 84 2 0
    //   600: istore 57
    //   602: aload_1
    //   603: ldc 171
    //   605: invokeinterface 84 2 0
    //   610: istore 58
    //   612: ldc 173
    //   614: ldc 163
    //   616: invokestatic 139	bv:a	(Ljava/lang/String;Ljava/lang/String;)Ljava/lang/String;
    //   619: astore 59
    //   621: aload_1
    //   622: aload 59
    //   624: invokeinterface 84 2 0
    //   629: istore 60
    //   631: ldc 173
    //   633: ldc 163
    //   635: ldc 161
    //   637: invokestatic 145	bv:a	(Ljava/lang/String;Ljava/lang/String;Ljava/lang/String;)Ljava/lang/String;
    //   640: astore 61
    //   642: aload_1
    //   643: aload 61
    //   645: invokeinterface 84 2 0
    //   650: istore 62
    //   652: ldc 153
    //   654: ldc 175
    //   656: invokestatic 139	bv:a	(Ljava/lang/String;Ljava/lang/String;)Ljava/lang/String;
    //   659: astore 63
    //   661: aload_1
    //   662: aload 63
    //   664: invokeinterface 84 2 0
    //   669: istore 64
    //   671: ldc 153
    //   673: ldc 175
    //   675: ldc 161
    //   677: invokestatic 145	bv:a	(Ljava/lang/String;Ljava/lang/String;Ljava/lang/String;)Ljava/lang/String;
    //   680: astore 65
    //   682: aload_1
    //   683: aload 65
    //   685: invokeinterface 84 2 0
    //   690: istore 66
    //   692: ldc 153
    //   694: ldc 177
    //   696: invokestatic 139	bv:a	(Ljava/lang/String;Ljava/lang/String;)Ljava/lang/String;
    //   699: astore 67
    //   701: aload_1
    //   702: aload 67
    //   704: invokeinterface 84 2 0
    //   709: istore 68
    //   711: ldc 153
    //   713: ldc 177
    //   715: ldc 161
    //   717: invokestatic 145	bv:a	(Ljava/lang/String;Ljava/lang/String;Ljava/lang/String;)Ljava/lang/String;
    //   720: astore 69
    //   722: aload_1
    //   723: aload 69
    //   725: invokeinterface 84 2 0
    //   730: istore 70
    //   732: ldc 153
    //   734: ldc 179
    //   736: invokestatic 139	bv:a	(Ljava/lang/String;Ljava/lang/String;)Ljava/lang/String;
    //   739: astore 71
    //   741: aload_1
    //   742: aload 71
    //   744: invokeinterface 84 2 0
    //   749: istore 72
    //   751: ldc 153
    //   753: ldc 179
    //   755: ldc 161
    //   757: invokestatic 145	bv:a	(Ljava/lang/String;Ljava/lang/String;Ljava/lang/String;)Ljava/lang/String;
    //   760: astore 73
    //   762: aload_1
    //   763: aload 73
    //   765: invokeinterface 84 2 0
    //   770: istore 74
    //   772: ldc 181
    //   774: ldc 163
    //   776: invokestatic 139	bv:a	(Ljava/lang/String;Ljava/lang/String;)Ljava/lang/String;
    //   779: astore 75
    //   781: aload_1
    //   782: aload 75
    //   784: invokeinterface 84 2 0
    //   789: istore 76
    //   791: ldc 181
    //   793: ldc 163
    //   795: ldc 161
    //   797: invokestatic 145	bv:a	(Ljava/lang/String;Ljava/lang/String;Ljava/lang/String;)Ljava/lang/String;
    //   800: astore 77
    //   802: aload_1
    //   803: aload 77
    //   805: invokeinterface 84 2 0
    //   810: istore 78
    //   812: ldc 183
    //   814: ldc 163
    //   816: invokestatic 139	bv:a	(Ljava/lang/String;Ljava/lang/String;)Ljava/lang/String;
    //   819: astore 79
    //   821: aload_1
    //   822: aload 79
    //   824: invokeinterface 84 2 0
    //   829: istore 80
    //   831: ldc 183
    //   833: ldc 163
    //   835: ldc 161
    //   837: invokestatic 145	bv:a	(Ljava/lang/String;Ljava/lang/String;Ljava/lang/String;)Ljava/lang/String;
    //   840: astore 81
    //   842: aload_1
    //   843: aload 81
    //   845: invokeinterface 84 2 0
    //   850: istore 82
    //   852: ldc 183
    //   854: ldc 165
    //   856: invokestatic 139	bv:a	(Ljava/lang/String;Ljava/lang/String;)Ljava/lang/String;
    //   859: astore 83
    //   861: aload_1
    //   862: aload 83
    //   864: invokeinterface 84 2 0
    //   869: istore 84
    //   871: ldc 183
    //   873: ldc 165
    //   875: ldc 161
    //   877: invokestatic 145	bv:a	(Ljava/lang/String;Ljava/lang/String;Ljava/lang/String;)Ljava/lang/String;
    //   880: astore 85
    //   882: aload_1
    //   883: aload 85
    //   885: invokeinterface 84 2 0
    //   890: istore 86
    //   892: aload_1
    //   893: ldc 185
    //   895: invokeinterface 84 2 0
    //   900: istore 87
    //   902: aload_1
    //   903: ldc 187
    //   905: invokeinterface 84 2 0
    //   910: istore 88
    //   912: aload_1
    //   913: ldc 189
    //   915: invokeinterface 84 2 0
    //   920: istore 89
    //   922: ldc 191
    //   924: ldc 163
    //   926: invokestatic 139	bv:a	(Ljava/lang/String;Ljava/lang/String;)Ljava/lang/String;
    //   929: astore 90
    //   931: aload_1
    //   932: aload 90
    //   934: invokeinterface 84 2 0
    //   939: istore 91
    //   941: ldc 191
    //   943: ldc 163
    //   945: ldc 161
    //   947: invokestatic 145	bv:a	(Ljava/lang/String;Ljava/lang/String;Ljava/lang/String;)Ljava/lang/String;
    //   950: astore 92
    //   952: aload_1
    //   953: aload 92
    //   955: invokeinterface 84 2 0
    //   960: istore 93
    //   962: ldc 193
    //   964: ldc 195
    //   966: invokestatic 139	bv:a	(Ljava/lang/String;Ljava/lang/String;)Ljava/lang/String;
    //   969: astore 94
    //   971: aload_1
    //   972: aload 94
    //   974: invokeinterface 84 2 0
    //   979: istore 95
    //   981: ldc 193
    //   983: ldc 195
    //   985: ldc 193
    //   987: invokestatic 145	bv:a	(Ljava/lang/String;Ljava/lang/String;Ljava/lang/String;)Ljava/lang/String;
    //   990: astore 96
    //   992: aload_1
    //   993: aload 96
    //   995: invokeinterface 84 2 0
    //   1000: istore 97
    //   1002: ldc 197
    //   1004: ldc 195
    //   1006: invokestatic 139	bv:a	(Ljava/lang/String;Ljava/lang/String;)Ljava/lang/String;
    //   1009: astore 98
    //   1011: aload_1
    //   1012: aload 98
    //   1014: invokeinterface 84 2 0
    //   1019: istore 99
    //   1021: ldc 197
    //   1023: ldc 195
    //   1025: ldc 193
    //   1027: invokestatic 145	bv:a	(Ljava/lang/String;Ljava/lang/String;Ljava/lang/String;)Ljava/lang/String;
    //   1030: astore 100
    //   1032: aload_1
    //   1033: aload 100
    //   1035: invokeinterface 84 2 0
    //   1040: istore 101
    //   1042: ldc 199
    //   1044: ldc 195
    //   1046: invokestatic 139	bv:a	(Ljava/lang/String;Ljava/lang/String;)Ljava/lang/String;
    //   1049: astore 102
    //   1051: aload_1
    //   1052: aload 102
    //   1054: invokeinterface 84 2 0
    //   1059: istore 103
    //   1061: ldc 199
    //   1063: ldc 195
    //   1065: ldc 193
    //   1067: invokestatic 145	bv:a	(Ljava/lang/String;Ljava/lang/String;Ljava/lang/String;)Ljava/lang/String;
    //   1070: astore 104
    //   1072: aload_1
    //   1073: aload 104
    //   1075: invokeinterface 84 2 0
    //   1080: istore 105
    //   1082: ldc 201
    //   1084: ldc 203
    //   1086: invokestatic 139	bv:a	(Ljava/lang/String;Ljava/lang/String;)Ljava/lang/String;
    //   1089: astore 106
    //   1091: aload_1
    //   1092: aload 106
    //   1094: invokeinterface 84 2 0
    //   1099: istore 107
    //   1101: ldc 201
    //   1103: ldc 203
    //   1105: ldc 193
    //   1107: invokestatic 145	bv:a	(Ljava/lang/String;Ljava/lang/String;Ljava/lang/String;)Ljava/lang/String;
    //   1110: astore 108
    //   1112: aload_1
    //   1113: aload 108
    //   1115: invokeinterface 84 2 0
    //   1120: istore 109
    //   1122: ldc 193
    //   1124: ldc 205
    //   1126: invokestatic 139	bv:a	(Ljava/lang/String;Ljava/lang/String;)Ljava/lang/String;
    //   1129: astore 110
    //   1131: aload_1
    //   1132: aload 110
    //   1134: invokeinterface 84 2 0
    //   1139: istore 111
    //   1141: ldc 193
    //   1143: ldc 205
    //   1145: ldc 193
    //   1147: invokestatic 145	bv:a	(Ljava/lang/String;Ljava/lang/String;Ljava/lang/String;)Ljava/lang/String;
    //   1150: astore 112
    //   1152: aload_1
    //   1153: aload 112
    //   1155: invokeinterface 84 2 0
    //   1160: istore 113
    //   1162: ldc 147
    //   1164: ldc 207
    //   1166: invokestatic 139	bv:a	(Ljava/lang/String;Ljava/lang/String;)Ljava/lang/String;
    //   1169: astore 114
    //   1171: aload_1
    //   1172: aload 114
    //   1174: invokeinterface 84 2 0
    //   1179: istore 115
    //   1181: ldc 147
    //   1183: ldc 207
    //   1185: ldc 193
    //   1187: invokestatic 145	bv:a	(Ljava/lang/String;Ljava/lang/String;Ljava/lang/String;)Ljava/lang/String;
    //   1190: astore 116
    //   1192: aload_1
    //   1193: aload 116
    //   1195: invokeinterface 84 2 0
    //   1200: istore 117
    //   1202: ldc 147
    //   1204: ldc 209
    //   1206: invokestatic 139	bv:a	(Ljava/lang/String;Ljava/lang/String;)Ljava/lang/String;
    //   1209: astore 118
    //   1211: aload_1
    //   1212: aload 118
    //   1214: invokeinterface 84 2 0
    //   1219: istore 119
    //   1221: ldc 147
    //   1223: ldc 209
    //   1225: ldc 193
    //   1227: invokestatic 145	bv:a	(Ljava/lang/String;Ljava/lang/String;Ljava/lang/String;)Ljava/lang/String;
    //   1230: astore 120
    //   1232: aload_1
    //   1233: aload 120
    //   1235: invokeinterface 84 2 0
    //   1240: istore 121
    //   1242: ldc 161
    //   1244: ldc 203
    //   1246: invokestatic 139	bv:a	(Ljava/lang/String;Ljava/lang/String;)Ljava/lang/String;
    //   1249: astore 122
    //   1251: aload_1
    //   1252: aload 122
    //   1254: invokeinterface 84 2 0
    //   1259: istore 123
    //   1261: ldc 161
    //   1263: ldc 203
    //   1265: ldc 193
    //   1267: invokestatic 145	bv:a	(Ljava/lang/String;Ljava/lang/String;Ljava/lang/String;)Ljava/lang/String;
    //   1270: astore 124
    //   1272: aload_1
    //   1273: aload 124
    //   1275: invokeinterface 84 2 0
    //   1280: istore 125
    //   1282: ldc 141
    //   1284: ldc 195
    //   1286: invokestatic 139	bv:a	(Ljava/lang/String;Ljava/lang/String;)Ljava/lang/String;
    //   1289: astore 126
    //   1291: aload_1
    //   1292: aload 126
    //   1294: invokeinterface 84 2 0
    //   1299: istore 127
    //   1301: ldc 141
    //   1303: ldc 195
    //   1305: ldc 193
    //   1307: invokestatic 145	bv:a	(Ljava/lang/String;Ljava/lang/String;Ljava/lang/String;)Ljava/lang/String;
    //   1310: astore 128
    //   1312: aload_1
    //   1313: aload 128
    //   1315: invokeinterface 84 2 0
    //   1320: istore 129
    //   1322: ldc 181
    //   1324: ldc 195
    //   1326: invokestatic 139	bv:a	(Ljava/lang/String;Ljava/lang/String;)Ljava/lang/String;
    //   1329: astore 130
    //   1331: aload_1
    //   1332: aload 130
    //   1334: invokeinterface 84 2 0
    //   1339: istore 131
    //   1341: ldc 181
    //   1343: ldc 195
    //   1345: ldc 193
    //   1347: invokestatic 145	bv:a	(Ljava/lang/String;Ljava/lang/String;Ljava/lang/String;)Ljava/lang/String;
    //   1350: astore 132
    //   1352: aload_1
    //   1353: aload 132
    //   1355: invokeinterface 84 2 0
    //   1360: istore 133
    //   1362: ldc 153
    //   1364: ldc 195
    //   1366: invokestatic 139	bv:a	(Ljava/lang/String;Ljava/lang/String;)Ljava/lang/String;
    //   1369: astore 134
    //   1371: aload_1
    //   1372: aload 134
    //   1374: invokeinterface 84 2 0
    //   1379: istore 135
    //   1381: ldc 153
    //   1383: ldc 195
    //   1385: ldc 193
    //   1387: invokestatic 145	bv:a	(Ljava/lang/String;Ljava/lang/String;Ljava/lang/String;)Ljava/lang/String;
    //   1390: astore 136
    //   1392: aload_1
    //   1393: aload 136
    //   1395: invokeinterface 84 2 0
    //   1400: istore 137
    //   1402: ldc 211
    //   1404: ldc 195
    //   1406: invokestatic 139	bv:a	(Ljava/lang/String;Ljava/lang/String;)Ljava/lang/String;
    //   1409: astore 138
    //   1411: aload_1
    //   1412: aload 138
    //   1414: invokeinterface 84 2 0
    //   1419: istore 139
    //   1421: ldc 211
    //   1423: ldc 195
    //   1425: ldc 193
    //   1427: invokestatic 145	bv:a	(Ljava/lang/String;Ljava/lang/String;Ljava/lang/String;)Ljava/lang/String;
    //   1430: astore 140
    //   1432: aload_1
    //   1433: aload 140
    //   1435: invokeinterface 84 2 0
    //   1440: istore 141
    //   1442: ldc 213
    //   1444: ldc 195
    //   1446: invokestatic 139	bv:a	(Ljava/lang/String;Ljava/lang/String;)Ljava/lang/String;
    //   1449: astore 142
    //   1451: aload_1
    //   1452: aload 142
    //   1454: invokeinterface 84 2 0
    //   1459: istore 143
    //   1461: ldc 213
    //   1463: ldc 195
    //   1465: ldc 193
    //   1467: invokestatic 145	bv:a	(Ljava/lang/String;Ljava/lang/String;Ljava/lang/String;)Ljava/lang/String;
    //   1470: astore 144
    //   1472: aload_1
    //   1473: aload 144
    //   1475: invokeinterface 84 2 0
    //   1480: istore 145
    //   1482: ldc 211
    //   1484: ldc 205
    //   1486: invokestatic 139	bv:a	(Ljava/lang/String;Ljava/lang/String;)Ljava/lang/String;
    //   1489: astore 146
    //   1491: aload_1
    //   1492: aload 146
    //   1494: invokeinterface 84 2 0
    //   1499: istore 147
    //   1501: ldc 211
    //   1503: ldc 205
    //   1505: ldc 193
    //   1507: invokestatic 145	bv:a	(Ljava/lang/String;Ljava/lang/String;Ljava/lang/String;)Ljava/lang/String;
    //   1510: astore 148
    //   1512: aload_1
    //   1513: aload 148
    //   1515: invokeinterface 84 2 0
    //   1520: istore 149
    //   1522: ldc 159
    //   1524: ldc 207
    //   1526: invokestatic 139	bv:a	(Ljava/lang/String;Ljava/lang/String;)Ljava/lang/String;
    //   1529: astore 150
    //   1531: aload_1
    //   1532: aload 150
    //   1534: invokeinterface 84 2 0
    //   1539: istore 151
    //   1541: ldc 159
    //   1543: ldc 207
    //   1545: ldc 193
    //   1547: invokestatic 145	bv:a	(Ljava/lang/String;Ljava/lang/String;Ljava/lang/String;)Ljava/lang/String;
    //   1550: astore 152
    //   1552: aload_1
    //   1553: aload 152
    //   1555: invokeinterface 84 2 0
    //   1560: istore 153
    //   1562: ldc 159
    //   1564: ldc 209
    //   1566: invokestatic 139	bv:a	(Ljava/lang/String;Ljava/lang/String;)Ljava/lang/String;
    //   1569: astore 154
    //   1571: aload_1
    //   1572: aload 154
    //   1574: invokeinterface 84 2 0
    //   1579: istore 155
    //   1581: ldc 159
    //   1583: ldc 209
    //   1585: ldc 193
    //   1587: invokestatic 145	bv:a	(Ljava/lang/String;Ljava/lang/String;Ljava/lang/String;)Ljava/lang/String;
    //   1590: astore 156
    //   1592: aload_1
    //   1593: aload 156
    //   1595: invokeinterface 84 2 0
    //   1600: istore 157
    //   1602: ldc 181
    //   1604: ldc 215
    //   1606: invokestatic 139	bv:a	(Ljava/lang/String;Ljava/lang/String;)Ljava/lang/String;
    //   1609: astore 158
    //   1611: aload_1
    //   1612: aload 158
    //   1614: invokeinterface 84 2 0
    //   1619: istore 159
    //   1621: ldc 181
    //   1623: ldc 215
    //   1625: ldc 181
    //   1627: invokestatic 145	bv:a	(Ljava/lang/String;Ljava/lang/String;Ljava/lang/String;)Ljava/lang/String;
    //   1630: astore 160
    //   1632: aload_1
    //   1633: aload 160
    //   1635: invokeinterface 84 2 0
    //   1640: istore 161
    //   1642: ldc 147
    //   1644: ldc 217
    //   1646: invokestatic 139	bv:a	(Ljava/lang/String;Ljava/lang/String;)Ljava/lang/String;
    //   1649: astore 162
    //   1651: aload_1
    //   1652: aload 162
    //   1654: invokeinterface 84 2 0
    //   1659: istore 163
    //   1661: ldc 147
    //   1663: ldc 217
    //   1665: ldc 147
    //   1667: invokestatic 145	bv:a	(Ljava/lang/String;Ljava/lang/String;Ljava/lang/String;)Ljava/lang/String;
    //   1670: astore 164
    //   1672: aload_1
    //   1673: aload 164
    //   1675: invokeinterface 84 2 0
    //   1680: istore 165
    //   1682: ldc 173
    //   1684: ldc 217
    //   1686: invokestatic 139	bv:a	(Ljava/lang/String;Ljava/lang/String;)Ljava/lang/String;
    //   1689: astore 166
    //   1691: aload_1
    //   1692: aload 166
    //   1694: invokeinterface 84 2 0
    //   1699: istore 167
    //   1701: ldc 173
    //   1703: ldc 217
    //   1705: ldc 147
    //   1707: invokestatic 145	bv:a	(Ljava/lang/String;Ljava/lang/String;Ljava/lang/String;)Ljava/lang/String;
    //   1710: astore 168
    //   1712: aload_1
    //   1713: aload 168
    //   1715: invokeinterface 84 2 0
    //   1720: istore 169
    //   1722: aload_1
    //   1723: ldc 219
    //   1725: invokeinterface 84 2 0
    //   1730: istore 170
    //   1732: aload_1
    //   1733: ldc 221
    //   1735: invokeinterface 84 2 0
    //   1740: istore 171
    //   1742: ldc 159
    //   1744: ldc 217
    //   1746: invokestatic 139	bv:a	(Ljava/lang/String;Ljava/lang/String;)Ljava/lang/String;
    //   1749: astore 172
    //   1751: aload_1
    //   1752: aload 172
    //   1754: invokeinterface 84 2 0
    //   1759: istore 173
    //   1761: ldc 159
    //   1763: ldc 217
    //   1765: ldc 147
    //   1767: invokestatic 145	bv:a	(Ljava/lang/String;Ljava/lang/String;Ljava/lang/String;)Ljava/lang/String;
    //   1770: astore 174
    //   1772: aload_1
    //   1773: aload 174
    //   1775: invokeinterface 84 2 0
    //   1780: istore 175
    //   1782: ldc 191
    //   1784: ldc 217
    //   1786: invokestatic 139	bv:a	(Ljava/lang/String;Ljava/lang/String;)Ljava/lang/String;
    //   1789: astore 176
    //   1791: aload_1
    //   1792: aload 176
    //   1794: invokeinterface 84 2 0
    //   1799: istore 177
    //   1801: ldc 191
    //   1803: ldc 217
    //   1805: ldc 147
    //   1807: invokestatic 145	bv:a	(Ljava/lang/String;Ljava/lang/String;Ljava/lang/String;)Ljava/lang/String;
    //   1810: astore 178
    //   1812: aload_1
    //   1813: aload 178
    //   1815: invokeinterface 84 2 0
    //   1820: istore 179
    //   1822: aload_1
    //   1823: ldc 223
    //   1825: invokeinterface 84 2 0
    //   1830: istore 180
    //   1832: aload_1
    //   1833: ldc 225
    //   1835: invokeinterface 84 2 0
    //   1840: istore 181
    //   1842: ldc 173
    //   1844: ldc 227
    //   1846: invokestatic 139	bv:a	(Ljava/lang/String;Ljava/lang/String;)Ljava/lang/String;
    //   1849: astore 182
    //   1851: aload_1
    //   1852: aload 182
    //   1854: invokeinterface 84 2 0
    //   1859: istore 183
    //   1861: ldc 173
    //   1863: ldc 227
    //   1865: ldc 173
    //   1867: invokestatic 145	bv:a	(Ljava/lang/String;Ljava/lang/String;Ljava/lang/String;)Ljava/lang/String;
    //   1870: astore 184
    //   1872: aload_1
    //   1873: aload 184
    //   1875: invokeinterface 84 2 0
    //   1880: istore 185
    //   1882: aload_1
    //   1883: ldc 229
    //   1885: invokeinterface 84 2 0
    //   1890: istore 186
    //   1892: aload_1
    //   1893: ldc 231
    //   1895: invokeinterface 84 2 0
    //   1900: istore 187
    //   1902: new 12	java/lang/StringBuilder
    //   1905: dup
    //   1906: invokespecial 13	java/lang/StringBuilder:<init>	()V
    //   1909: ldc 233
    //   1911: invokevirtual 19	java/lang/StringBuilder:append	(Ljava/lang/String;)Ljava/lang/StringBuilder;
    //   1914: ldc2_w 234
    //   1917: invokevirtual 238	java/lang/StringBuilder:append	(J)Ljava/lang/StringBuilder;
    //   1920: ldc 240
    //   1922: invokevirtual 19	java/lang/StringBuilder:append	(Ljava/lang/String;)Ljava/lang/StringBuilder;
    //   1925: ldc 242
    //   1927: invokevirtual 19	java/lang/StringBuilder:append	(Ljava/lang/String;)Ljava/lang/StringBuilder;
    //   1930: ldc 244
    //   1932: invokevirtual 19	java/lang/StringBuilder:append	(Ljava/lang/String;)Ljava/lang/StringBuilder;
    //   1935: invokevirtual 29	java/lang/StringBuilder:toString	()Ljava/lang/String;
    //   1938: astore 188
    //   1940: aload_1
    //   1941: aload 188
    //   1943: invokeinterface 84 2 0
    //   1948: istore 189
    //   1950: aload_1
    //   1951: ldc 245
    //   1953: invokestatic 250	he:a	(Ljava/util/List;Z)V
    //   1956: aload_1
    //   1957: invokeinterface 253 1 0
    //   1962: invokestatic 258	g:a	()Lg;
    //   1965: invokevirtual 262	g:f	()Ln;
    //   1968: invokeinterface 267 1 0
    //   1973: invokevirtual 272	hp:a	()J
    //   1976: putstatic 278	com/mymoney/core/application/ApplicationContext:d	J
    //   1979: ldc 64
    //   1981: ldc_w 280
    //   1984: invokestatic 71	gj:a	(Ljava/lang/String;Ljava/lang/String;)V
    //   1987: iconst_1
    //   1988: ireturn
    //   1989: astore 190
    //   1991: aconst_null
    //   1992: astore 191
    //   1994: aload 191
    //   1996: invokeinterface 125 1 0
    //   2001: aload 190
    //   2003: athrow
    //   2004: astore 190
    //   2006: aload 10
    //   2008: astore 191
    //   2010: goto -16 -> 1994
    //
    // Exception table:
    //   from	to	target	type
    //   91	103	1989	finally
    //   107	139	2004	finally
  }
}

/* Location:           F:\soft\android\soft\dex2jar-0.0.7.10-SNAPSHOT\classes.dex.dex2jar.jar
 * Qualified Name:     bv
 * JD-Core Version:    0.6.0
 */