import android.content.Context;
import com.mymoney.core.application.ApplicationContext;
import java.util.ArrayList;
import java.util.List;

public class fu
{
  public static String a = "SyncEngine";
  String b;
  private fy c;
  private boolean d;

  public fu(fy paramfy)
  {
    fw localfw = new fw();
    this.c = localfw;
    this.d = 0;
    StringBuilder localStringBuilder = new StringBuilder().append("/data/data/");
    String str1 = ApplicationContext.a.getPackageName();
    String str2 = str1;
    this.b = str2;
    if (paramfy == null)
      return;
    this.c = paramfy;
  }

  private void b()
  {
    ArrayList localArrayList = new ArrayList();
    boolean bool1 = localArrayList.add("delete from t_account");
    boolean bool2 = localArrayList.add("delete from t_budget_item where categoryPOID <> 0");
    boolean bool3 = localArrayList.add("delete from t_category where depth > 0");
    boolean bool4 = localArrayList.add("delete from t_tradingEntity");
    boolean bool5 = localArrayList.add("delete from t_tag where tagType = 1");
    he.a(localArrayList, 1);
  }

  private void c()
  {
    ArrayList localArrayList = new ArrayList();
    StringBuilder localStringBuilder = new StringBuilder().append("update t_metadata set agentVersion = '");
    String str1 = gt.e();
    String str2 = str1 + "' ";
    boolean bool = localArrayList.add(str2);
    he.a(localArrayList, 1);
  }

  private void d()
  {
  }

  /** @deprecated */
  // ERROR //
  public String a(ff paramff, fg paramfg)
  {
    // Byte code:
    //   0: aload_0
    //   1: monitorenter
    //   2: aconst_null
    //   3: astore_3
    //   4: aconst_null
    //   5: astore 4
    //   7: aconst_null
    //   8: astore 5
    //   10: invokestatic 100	gt:a	()J
    //   13: lstore 6
    //   15: ldc 102
    //   17: astore 8
    //   19: ldc 102
    //   21: astore 9
    //   23: aconst_null
    //   24: astore 10
    //   26: aload_0
    //   27: invokespecial 104	fu:c	()V
    //   30: invokestatic 108	fp:b	()V
    //   33: invokestatic 114	gu:j	()Z
    //   36: ifeq +7 -> 43
    //   39: aload_0
    //   40: invokespecial 115	fu:b	()V
    //   43: new 117	fs
    //   46: astore 11
    //   48: aload_0
    //   49: getfield 26	fu:c	Lfy;
    //   52: astore 12
    //   54: aload 11
    //   56: astore 13
    //   58: aload_1
    //   59: astore 14
    //   61: aload_2
    //   62: astore 15
    //   64: aload 12
    //   66: astore 16
    //   68: aload 13
    //   70: aload 14
    //   72: aload 15
    //   74: aload 16
    //   76: invokespecial 120	fs:<init>	(Lff;Lfg;Lfy;)V
    //   79: aload 11
    //   81: invokevirtual 122	fs:a	()V
    //   84: getstatic 17	fu:a	Ljava/lang/String;
    //   87: astore 17
    //   89: new 31	java/lang/StringBuilder
    //   92: dup
    //   93: invokespecial 32	java/lang/StringBuilder:<init>	()V
    //   96: ldc 124
    //   98: invokevirtual 38	java/lang/StringBuilder:append	(Ljava/lang/String;)Ljava/lang/StringBuilder;
    //   101: astore 18
    //   103: invokestatic 100	gt:a	()J
    //   106: lload 6
    //   108: lsub
    //   109: ldc2_w 125
    //   112: ldiv
    //   113: lstore 19
    //   115: aload 18
    //   117: lload 19
    //   119: invokevirtual 129	java/lang/StringBuilder:append	(J)Ljava/lang/StringBuilder;
    //   122: ldc 131
    //   124: invokevirtual 38	java/lang/StringBuilder:append	(Ljava/lang/String;)Ljava/lang/StringBuilder;
    //   127: invokevirtual 52	java/lang/StringBuilder:toString	()Ljava/lang/String;
    //   130: astore 21
    //   132: aload 17
    //   134: aload 21
    //   136: invokestatic 136	gj:a	(Ljava/lang/String;Ljava/lang/String;)V
    //   139: aload_0
    //   140: getfield 26	fu:c	Lfy;
    //   143: invokeinterface 139 1 0
    //   148: new 141	fq
    //   151: astore 22
    //   153: aload_0
    //   154: getfield 26	fu:c	Lfy;
    //   157: astore 23
    //   159: aload 22
    //   161: astore 24
    //   163: aload_1
    //   164: astore 25
    //   166: aload_2
    //   167: astore 26
    //   169: aload 23
    //   171: astore 27
    //   173: aload 24
    //   175: aload 25
    //   177: aload 26
    //   179: aload 27
    //   181: invokespecial 142	fq:<init>	(Lff;Lfg;Lfy;)V
    //   184: aload 22
    //   186: invokevirtual 143	fq:a	()V
    //   189: aload 22
    //   191: invokevirtual 147	fq:f	()I
    //   194: istore 28
    //   196: aload 22
    //   198: getfield 149	fq:a	Z
    //   201: ifeq +411 -> 612
    //   204: new 151	fo
    //   207: astore 29
    //   209: aload_0
    //   210: getfield 26	fu:c	Lfy;
    //   213: astore 30
    //   215: aload 29
    //   217: astore 31
    //   219: aload_1
    //   220: astore 32
    //   222: aload_2
    //   223: astore 33
    //   225: aload 30
    //   227: astore 34
    //   229: aload 31
    //   231: aload 32
    //   233: aload 33
    //   235: aload 34
    //   237: invokespecial 152	fo:<init>	(Lff;Lfg;Lfy;)V
    //   240: aload 29
    //   242: invokevirtual 153	fo:a	()V
    //   245: aload 29
    //   247: getfield 155	fo:b	Z
    //   250: ifeq +352 -> 602
    //   253: new 157	fv
    //   256: astore 35
    //   258: aload_0
    //   259: getfield 26	fu:c	Lfy;
    //   262: astore 36
    //   264: aload 35
    //   266: astore 37
    //   268: aload_1
    //   269: astore 38
    //   271: aload_2
    //   272: astore 39
    //   274: aload 36
    //   276: astore 40
    //   278: aload 37
    //   280: aload 38
    //   282: aload 39
    //   284: aload 40
    //   286: invokespecial 158	fv:<init>	(Lff;Lfg;Lfy;)V
    //   289: aload 35
    //   291: invokevirtual 159	fv:a	()V
    //   294: aload 29
    //   296: invokevirtual 161	fo:b	()Ljava/lang/String;
    //   299: astore 41
    //   301: aload 41
    //   303: astore 42
    //   305: aconst_null
    //   306: astore 43
    //   308: aload 43
    //   310: ifnonnull +322 -> 632
    //   313: aload 22
    //   315: invokevirtual 162	fq:e	()Ljava/lang/String;
    //   318: astore 41
    //   320: aload 41
    //   322: astore 44
    //   324: new 31	java/lang/StringBuilder
    //   327: dup
    //   328: invokespecial 32	java/lang/StringBuilder:<init>	()V
    //   331: ldc 164
    //   333: invokevirtual 38	java/lang/StringBuilder:append	(Ljava/lang/String;)Ljava/lang/StringBuilder;
    //   336: astore 45
    //   338: aload 22
    //   340: invokevirtual 147	fq:f	()I
    //   343: istore 46
    //   345: aload 45
    //   347: iload 46
    //   349: invokevirtual 167	java/lang/StringBuilder:append	(I)Ljava/lang/StringBuilder;
    //   352: invokevirtual 52	java/lang/StringBuilder:toString	()Ljava/lang/String;
    //   355: astore 47
    //   357: iload 28
    //   359: ifne +25 -> 384
    //   362: new 31	java/lang/StringBuilder
    //   365: dup
    //   366: invokespecial 32	java/lang/StringBuilder:<init>	()V
    //   369: ldc 169
    //   371: invokevirtual 38	java/lang/StringBuilder:append	(Ljava/lang/String;)Ljava/lang/StringBuilder;
    //   374: aload 44
    //   376: invokevirtual 38	java/lang/StringBuilder:append	(Ljava/lang/String;)Ljava/lang/StringBuilder;
    //   379: invokevirtual 52	java/lang/StringBuilder:toString	()Ljava/lang/String;
    //   382: astore 47
    //   384: new 91	ej
    //   387: dup
    //   388: aload 47
    //   390: invokespecial 172	ej:<init>	(Ljava/lang/String;)V
    //   393: athrow
    //   394: astore 48
    //   396: aconst_null
    //   397: astore 9
    //   399: iload 28
    //   401: istore 5
    //   403: aload 43
    //   405: astore 10
    //   407: aload 44
    //   409: astore 8
    //   411: aload 48
    //   413: astore 4
    //   415: aload 4
    //   417: invokevirtual 175	ej:printStackTrace	()V
    //   420: aconst_null
    //   421: astore_3
    //   422: aload_0
    //   423: invokespecial 177	fu:d	()V
    //   426: aload 4
    //   428: athrow
    //   429: astore 49
    //   431: aload 5
    //   433: astore 4
    //   435: aload 8
    //   437: astore 5
    //   439: aload 9
    //   441: astore 8
    //   443: aload 10
    //   445: astore 9
    //   447: aload_3
    //   448: astore 28
    //   450: aload 49
    //   452: astore_3
    //   453: aload 28
    //   455: ifnull +7 -> 462
    //   458: aload_0
    //   459: invokespecial 177	fu:d	()V
    //   462: aload 9
    //   464: ifnull +595 -> 1059
    //   467: ldc 27
    //   469: invokestatic 180	gu:d	(Z)V
    //   472: aload_0
    //   473: getfield 26	fu:c	Lfy;
    //   476: invokeinterface 181 1 0
    //   481: getstatic 17	fu:a	Ljava/lang/String;
    //   484: astore 50
    //   486: new 31	java/lang/StringBuilder
    //   489: dup
    //   490: invokespecial 32	java/lang/StringBuilder:<init>	()V
    //   493: ldc 183
    //   495: invokevirtual 38	java/lang/StringBuilder:append	(Ljava/lang/String;)Ljava/lang/StringBuilder;
    //   498: astore 51
    //   500: invokestatic 100	gt:a	()J
    //   503: lload 6
    //   505: lsub
    //   506: ldc2_w 125
    //   509: ldiv
    //   510: lstore 52
    //   512: aload 51
    //   514: lload 52
    //   516: invokevirtual 129	java/lang/StringBuilder:append	(J)Ljava/lang/StringBuilder;
    //   519: ldc 131
    //   521: invokevirtual 38	java/lang/StringBuilder:append	(Ljava/lang/String;)Ljava/lang/StringBuilder;
    //   524: invokevirtual 52	java/lang/StringBuilder:toString	()Ljava/lang/String;
    //   527: astore 54
    //   529: aload 50
    //   531: aload 54
    //   533: invokestatic 136	gj:a	(Ljava/lang/String;Ljava/lang/String;)V
    //   536: invokestatic 188	eb:a	()Leb;
    //   539: astore 55
    //   541: getstatic 193	ea:s	Ljava/lang/String;
    //   544: astore 56
    //   546: aload 55
    //   548: aload 56
    //   550: invokevirtual 195	eb:a	(Ljava/lang/String;)V
    //   553: aload_3
    //   554: athrow
    //   555: astore 57
    //   557: aload_0
    //   558: monitorexit
    //   559: aload 57
    //   561: athrow
    //   562: astore 43
    //   564: aload 43
    //   566: invokevirtual 196	ef:printStackTrace	()V
    //   569: new 95	ef
    //   572: dup
    //   573: ldc 198
    //   575: invokespecial 199	ef:<init>	(Ljava/lang/String;)V
    //   578: athrow
    //   579: astore 58
    //   581: aload 9
    //   583: astore 8
    //   585: aconst_null
    //   586: astore 9
    //   588: aload 10
    //   590: astore 5
    //   592: aconst_null
    //   593: astore 10
    //   595: aload 58
    //   597: astore 4
    //   599: goto -184 -> 415
    //   602: iconst_1
    //   603: istore 59
    //   605: aload 8
    //   607: astore 60
    //   609: goto -304 -> 305
    //   612: iload 28
    //   614: iconst_2
    //   615: if_icmpne +749 -> 1364
    //   618: aload 8
    //   620: astore 61
    //   622: iconst_0
    //   623: istore 62
    //   625: aload 61
    //   627: astore 63
    //   629: goto -321 -> 308
    //   632: invokestatic 204	g:a	()Lg;
    //   635: invokevirtual 208	g:h	()Lk;
    //   638: astore 22
    //   640: aload 22
    //   642: invokeinterface 212 1 0
    //   647: astore 29
    //   649: getstatic 214	com/mymoney/core/application/ApplicationContext:g	Ljava/lang/String;
    //   652: aload 29
    //   654: invokevirtual 220	java/lang/String:equalsIgnoreCase	(Ljava/lang/String;)Z
    //   657: ifne +14 -> 671
    //   660: aload 22
    //   662: aload 29
    //   664: invokeinterface 222 2 0
    //   669: istore 64
    //   671: getstatic 223	gu:s	Ljava/lang/String;
    //   674: astore 65
    //   676: invokestatic 225	gt:f	()J
    //   679: lstore 66
    //   681: aload 65
    //   683: lload 66
    //   685: invokestatic 228	gu:a	(Ljava/lang/String;J)V
    //   688: invokestatic 233	ai:a	()Lai;
    //   691: invokevirtual 236	ai:c	()Lac;
    //   694: astore 41
    //   696: aload 41
    //   698: astore 22
    //   700: aload 22
    //   702: invokeinterface 240 1 0
    //   707: ifeq +123 -> 830
    //   710: invokestatic 245	hq:a	()Lhq;
    //   713: ldc 27
    //   715: invokevirtual 247	hq:a	(Z)V
    //   718: getstatic 17	fu:a	Ljava/lang/String;
    //   721: ldc 249
    //   723: invokestatic 136	gj:a	(Ljava/lang/String;Ljava/lang/String;)V
    //   726: iconst_0
    //   727: ifeq +7 -> 734
    //   730: aload_0
    //   731: invokespecial 177	fu:d	()V
    //   734: aload 43
    //   736: ifnull +147 -> 883
    //   739: ldc 27
    //   741: invokestatic 180	gu:d	(Z)V
    //   744: aload_0
    //   745: getfield 26	fu:c	Lfy;
    //   748: invokeinterface 181 1 0
    //   753: getstatic 17	fu:a	Ljava/lang/String;
    //   756: astore 68
    //   758: new 31	java/lang/StringBuilder
    //   761: dup
    //   762: invokespecial 32	java/lang/StringBuilder:<init>	()V
    //   765: ldc 183
    //   767: invokevirtual 38	java/lang/StringBuilder:append	(Ljava/lang/String;)Ljava/lang/StringBuilder;
    //   770: astore 69
    //   772: invokestatic 100	gt:a	()J
    //   775: lload 6
    //   777: lsub
    //   778: ldc2_w 125
    //   781: ldiv
    //   782: lstore 70
    //   784: aload 69
    //   786: lload 70
    //   788: invokevirtual 129	java/lang/StringBuilder:append	(J)Ljava/lang/StringBuilder;
    //   791: ldc 131
    //   793: invokevirtual 38	java/lang/StringBuilder:append	(Ljava/lang/String;)Ljava/lang/StringBuilder;
    //   796: invokevirtual 52	java/lang/StringBuilder:toString	()Ljava/lang/String;
    //   799: astore 72
    //   801: aload 68
    //   803: aload 72
    //   805: invokestatic 136	gj:a	(Ljava/lang/String;Ljava/lang/String;)V
    //   808: invokestatic 188	eb:a	()Leb;
    //   811: astore 73
    //   813: getstatic 193	ea:s	Ljava/lang/String;
    //   816: astore 74
    //   818: aload 73
    //   820: aload 74
    //   822: invokevirtual 195	eb:a	(Ljava/lang/String;)V
    //   825: aload_0
    //   826: monitorexit
    //   827: aload 42
    //   829: areturn
    //   830: getstatic 17	fu:a	Ljava/lang/String;
    //   833: ldc 251
    //   835: invokestatic 136	gj:a	(Ljava/lang/String;Ljava/lang/String;)V
    //   838: goto -112 -> 726
    //   841: astore 22
    //   843: aload 22
    //   845: invokevirtual 252	java/lang/Exception:printStackTrace	()V
    //   848: getstatic 17	fu:a	Ljava/lang/String;
    //   851: ldc 254
    //   853: invokestatic 136	gj:a	(Ljava/lang/String;Ljava/lang/String;)V
    //   856: goto -130 -> 726
    //   859: astore 4
    //   861: iload 28
    //   863: istore 75
    //   865: aload 43
    //   867: astore 10
    //   869: aload 9
    //   871: astore 8
    //   873: aconst_null
    //   874: astore 9
    //   876: iload 75
    //   878: istore 5
    //   880: goto -465 -> 415
    //   883: iload 28
    //   885: ifne +50 -> 935
    //   888: new 256	fl
    //   891: astore 76
    //   893: aload_0
    //   894: getfield 26	fu:c	Lfy;
    //   897: astore 77
    //   899: aload 76
    //   901: astore 78
    //   903: aload_1
    //   904: astore 79
    //   906: aload_2
    //   907: astore 80
    //   909: aload 77
    //   911: astore 81
    //   913: aload 9
    //   915: astore 82
    //   917: aload 78
    //   919: aload 79
    //   921: aload 80
    //   923: aload 81
    //   925: aload 82
    //   927: invokespecial 259	fl:<init>	(Lff;Lfg;Lfy;Ljava/lang/String;)V
    //   930: aload 76
    //   932: invokevirtual 260	fl:a	()V
    //   935: iconst_0
    //   936: ifne +9 -> 945
    //   939: invokestatic 114	gu:j	()Z
    //   942: ifeq -198 -> 744
    //   945: invokestatic 261	fp:c	()V
    //   948: ldc 27
    //   950: invokestatic 263	gu:h	(Z)V
    //   953: goto -209 -> 744
    //   956: invokevirtual 252	java/lang/Exception:printStackTrace	()V
    //   959: goto -24 -> 935
    //   962: astore 83
    //   964: aload 9
    //   966: astore 8
    //   968: aconst_null
    //   969: astore 9
    //   971: aload 10
    //   973: astore 5
    //   975: aconst_null
    //   976: astore 10
    //   978: aload 83
    //   980: astore 4
    //   982: aload 4
    //   984: invokevirtual 264	ee:printStackTrace	()V
    //   987: aconst_null
    //   988: astore_3
    //   989: aload_0
    //   990: invokespecial 177	fu:d	()V
    //   993: aload 4
    //   995: athrow
    //   996: astore 84
    //   998: aload 9
    //   1000: astore 8
    //   1002: aconst_null
    //   1003: astore 9
    //   1005: aload 10
    //   1007: astore 5
    //   1009: aconst_null
    //   1010: astore 10
    //   1012: aload 84
    //   1014: astore 4
    //   1016: aload 4
    //   1018: invokevirtual 196	ef:printStackTrace	()V
    //   1021: new 95	ef
    //   1024: dup
    //   1025: ldc 198
    //   1027: invokespecial 199	ef:<init>	(Ljava/lang/String;)V
    //   1030: athrow
    //   1031: astore 85
    //   1033: aload 9
    //   1035: astore 8
    //   1037: aconst_null
    //   1038: astore 9
    //   1040: aload 10
    //   1042: astore 5
    //   1044: aconst_null
    //   1045: astore 10
    //   1047: aload 85
    //   1049: astore 4
    //   1051: aload 4
    //   1053: invokevirtual 252	java/lang/Exception:printStackTrace	()V
    //   1056: aload 4
    //   1058: athrow
    //   1059: aload 4
    //   1061: ifnonnull +50 -> 1111
    //   1064: new 256	fl
    //   1067: astore 86
    //   1069: aload_0
    //   1070: getfield 26	fu:c	Lfy;
    //   1073: astore 87
    //   1075: aload 86
    //   1077: astore 88
    //   1079: aload_1
    //   1080: astore 89
    //   1082: aload_2
    //   1083: astore 90
    //   1085: aload 87
    //   1087: astore 91
    //   1089: aload 5
    //   1091: astore 92
    //   1093: aload 88
    //   1095: aload 89
    //   1097: aload 90
    //   1099: aload 91
    //   1101: aload 92
    //   1103: invokespecial 259	fl:<init>	(Lff;Lfg;Lfy;Ljava/lang/String;)V
    //   1106: aload 86
    //   1108: invokevirtual 260	fl:a	()V
    //   1111: aload 8
    //   1113: ifnonnull +9 -> 1122
    //   1116: invokestatic 114	gu:j	()Z
    //   1119: ifeq -647 -> 472
    //   1122: invokestatic 261	fp:c	()V
    //   1125: ldc 27
    //   1127: invokestatic 263	gu:h	(Z)V
    //   1130: goto -658 -> 472
    //   1133: invokevirtual 252	java/lang/Exception:printStackTrace	()V
    //   1136: goto -25 -> 1111
    //   1139: astore 93
    //   1141: aconst_null
    //   1142: astore 8
    //   1144: aload 9
    //   1146: astore 5
    //   1148: aconst_null
    //   1149: astore 9
    //   1151: aload 10
    //   1153: astore 4
    //   1155: aconst_null
    //   1156: astore 28
    //   1158: aload 93
    //   1160: astore_3
    //   1161: goto -708 -> 453
    //   1164: astore 94
    //   1166: iload 28
    //   1168: istore 4
    //   1170: aconst_null
    //   1171: astore 28
    //   1173: aload 94
    //   1175: astore_3
    //   1176: aconst_null
    //   1177: astore 95
    //   1179: aload 9
    //   1181: astore 5
    //   1183: aload 43
    //   1185: astore 9
    //   1187: aload 95
    //   1189: astore 8
    //   1191: goto -738 -> 453
    //   1194: astore 96
    //   1196: aload 43
    //   1198: astore 9
    //   1200: aconst_null
    //   1201: astore 8
    //   1203: aload 44
    //   1205: astore 5
    //   1207: iload 28
    //   1209: istore 4
    //   1211: aconst_null
    //   1212: astore 28
    //   1214: aload 96
    //   1216: astore_3
    //   1217: goto -764 -> 453
    //   1220: astore 4
    //   1222: iload 28
    //   1224: istore 97
    //   1226: aload 43
    //   1228: astore 10
    //   1230: aload 9
    //   1232: astore 8
    //   1234: aconst_null
    //   1235: astore 9
    //   1237: iload 97
    //   1239: istore 5
    //   1241: goto -190 -> 1051
    //   1244: astore 98
    //   1246: aconst_null
    //   1247: astore 9
    //   1249: iload 28
    //   1251: istore 5
    //   1253: aload 43
    //   1255: astore 10
    //   1257: aload 44
    //   1259: astore 8
    //   1261: aload 98
    //   1263: astore 4
    //   1265: goto -214 -> 1051
    //   1268: astore 4
    //   1270: iload 28
    //   1272: istore 99
    //   1274: aload 43
    //   1276: astore 10
    //   1278: aload 9
    //   1280: astore 8
    //   1282: aconst_null
    //   1283: astore 9
    //   1285: iload 99
    //   1287: istore 5
    //   1289: goto -273 -> 1016
    //   1292: astore 100
    //   1294: aconst_null
    //   1295: astore 9
    //   1297: iload 28
    //   1299: istore 5
    //   1301: aload 43
    //   1303: astore 10
    //   1305: aload 44
    //   1307: astore 8
    //   1309: aload 100
    //   1311: astore 4
    //   1313: goto -297 -> 1016
    //   1316: astore 4
    //   1318: iload 28
    //   1320: istore 101
    //   1322: aload 43
    //   1324: astore 10
    //   1326: aload 9
    //   1328: astore 8
    //   1330: aconst_null
    //   1331: astore 9
    //   1333: iload 101
    //   1335: istore 5
    //   1337: goto -355 -> 982
    //   1340: astore 102
    //   1342: aconst_null
    //   1343: astore 9
    //   1345: iload 28
    //   1347: istore 5
    //   1349: aload 43
    //   1351: astore 10
    //   1353: aload 44
    //   1355: astore 8
    //   1357: aload 102
    //   1359: astore 4
    //   1361: goto -379 -> 982
    //   1364: aload 8
    //   1366: astore 103
    //   1368: aconst_null
    //   1369: astore 43
    //   1371: aload 103
    //   1373: astore 42
    //   1375: goto -1067 -> 308
    //
    // Exception table:
    //   from	to	target	type
    //   324	394	394	ej
    //   415	429	429	finally
    //   982	1059	429	finally
    //   10	23	555	finally
    //   458	555	555	finally
    //   730	825	555	finally
    //   888	935	555	finally
    //   939	959	555	finally
    //   1064	1111	555	finally
    //   1116	1136	555	finally
    //   43	139	562	ef
    //   26	43	579	ej
    //   43	139	579	ej
    //   139	301	579	ej
    //   564	579	579	ej
    //   700	726	841	java/lang/Exception
    //   830	838	841	java/lang/Exception
    //   313	320	859	ej
    //   632	696	859	ej
    //   700	726	859	ej
    //   830	838	859	ej
    //   843	856	859	ej
    //   888	935	956	java/lang/Exception
    //   26	43	962	ee
    //   43	139	962	ee
    //   139	301	962	ee
    //   564	579	962	ee
    //   26	43	996	ef
    //   139	301	996	ef
    //   564	579	996	ef
    //   26	43	1031	java/lang/Exception
    //   43	139	1031	java/lang/Exception
    //   139	301	1031	java/lang/Exception
    //   564	579	1031	java/lang/Exception
    //   1064	1111	1133	java/lang/Exception
    //   26	43	1139	finally
    //   43	139	1139	finally
    //   139	301	1139	finally
    //   564	579	1139	finally
    //   313	320	1164	finally
    //   632	696	1164	finally
    //   700	726	1164	finally
    //   830	838	1164	finally
    //   843	856	1164	finally
    //   324	394	1194	finally
    //   313	320	1220	java/lang/Exception
    //   632	696	1220	java/lang/Exception
    //   843	856	1220	java/lang/Exception
    //   324	394	1244	java/lang/Exception
    //   313	320	1268	ef
    //   632	696	1268	ef
    //   700	726	1268	ef
    //   830	838	1268	ef
    //   843	856	1268	ef
    //   324	394	1292	ef
    //   313	320	1316	ee
    //   632	696	1316	ee
    //   700	726	1316	ee
    //   830	838	1316	ee
    //   843	856	1316	ee
    //   324	394	1340	ee
  }

  public void a()
  {
    this.d = 1;
  }
}

/* Location:           F:\soft\android\soft\dex2jar-0.0.7.10-SNAPSHOT\classes.dex.dex2jar.jar
 * Qualified Name:     fu
 * JD-Core Version:    0.6.0
 */