public class gl
{
  // ERROR //
  public static final void a(java.io.File paramFile1, java.io.File paramFile2)
  {
    // Byte code:
    //   0: iconst_0
    //   1: istore_2
    //   2: aload_1
    //   3: invokevirtual 18	java/io/File:exists	()Z
    //   6: ifeq +8 -> 14
    //   9: aload_1
    //   10: invokevirtual 21	java/io/File:delete	()Z
    //   13: istore_3
    //   14: ldc 22
    //   16: newarray byte
    //   18: astore 4
    //   20: new 24	java/io/FileInputStream
    //   23: dup
    //   24: aload_0
    //   25: invokespecial 27	java/io/FileInputStream:<init>	(Ljava/io/File;)V
    //   28: astore 5
    //   30: new 29	java/io/BufferedInputStream
    //   33: dup
    //   34: aload 5
    //   36: invokespecial 32	java/io/BufferedInputStream:<init>	(Ljava/io/InputStream;)V
    //   39: astore 6
    //   41: new 34	java/io/FileOutputStream
    //   44: dup
    //   45: aload_1
    //   46: invokespecial 35	java/io/FileOutputStream:<init>	(Ljava/io/File;)V
    //   49: astore 7
    //   51: new 37	java/io/BufferedOutputStream
    //   54: dup
    //   55: aload 7
    //   57: invokespecial 40	java/io/BufferedOutputStream:<init>	(Ljava/io/OutputStream;)V
    //   60: astore 8
    //   62: aload 6
    //   64: aload 4
    //   66: invokevirtual 44	java/io/BufferedInputStream:read	([B)I
    //   69: istore_2
    //   70: iload_2
    //   71: bipush 255
    //   73: if_icmpeq +84 -> 157
    //   76: aload 8
    //   78: aload 4
    //   80: iconst_0
    //   81: iload_2
    //   82: invokevirtual 48	java/io/BufferedOutputStream:write	([BII)V
    //   85: goto -23 -> 62
    //   88: astore 9
    //   90: aload 8
    //   92: astore 10
    //   94: aload 5
    //   96: astore 11
    //   98: aload 10
    //   100: astore 12
    //   102: aload 6
    //   104: astore 13
    //   106: aload 7
    //   108: astore 14
    //   110: aload 13
    //   112: astore 15
    //   114: aload 12
    //   116: ifnull +8 -> 124
    //   119: aload 12
    //   121: invokevirtual 51	java/io/BufferedOutputStream:close	()V
    //   124: aload 15
    //   126: ifnull +8 -> 134
    //   129: aload 15
    //   131: invokevirtual 52	java/io/BufferedInputStream:close	()V
    //   134: aload 11
    //   136: ifnull +8 -> 144
    //   139: aload 11
    //   141: invokevirtual 53	java/io/FileInputStream:close	()V
    //   144: aload 14
    //   146: ifnull +8 -> 154
    //   149: aload 14
    //   151: invokevirtual 54	java/io/FileOutputStream:close	()V
    //   154: aload 9
    //   156: athrow
    //   157: aload 8
    //   159: invokevirtual 57	java/io/BufferedOutputStream:flush	()V
    //   162: aload 8
    //   164: ifnull +8 -> 172
    //   167: aload 8
    //   169: invokevirtual 51	java/io/BufferedOutputStream:close	()V
    //   172: aload 6
    //   174: ifnull +8 -> 182
    //   177: aload 6
    //   179: invokevirtual 52	java/io/BufferedInputStream:close	()V
    //   182: aload 5
    //   184: ifnull +8 -> 192
    //   187: aload 5
    //   189: invokevirtual 53	java/io/FileInputStream:close	()V
    //   192: aload 7
    //   194: ifnonnull +4 -> 198
    //   197: return
    //   198: aload 7
    //   200: invokevirtual 54	java/io/FileOutputStream:close	()V
    //   203: return
    //   204: astore 16
    //   206: goto -34 -> 172
    //   209: astore 17
    //   211: goto -29 -> 182
    //   214: astore 18
    //   216: goto -24 -> 192
    //   219: astore 19
    //   221: return
    //   222: astore 20
    //   224: goto -100 -> 124
    //   227: astore 21
    //   229: goto -95 -> 134
    //   232: astore 22
    //   234: goto -90 -> 144
    //   237: astore 23
    //   239: goto -85 -> 154
    //   242: astore 9
    //   244: aconst_null
    //   245: astore 12
    //   247: aconst_null
    //   248: astore 14
    //   250: aconst_null
    //   251: astore 15
    //   253: aconst_null
    //   254: astore 11
    //   256: goto -142 -> 114
    //   259: astore 9
    //   261: aconst_null
    //   262: astore 14
    //   264: aconst_null
    //   265: astore 15
    //   267: aload 5
    //   269: astore 11
    //   271: aconst_null
    //   272: astore 12
    //   274: goto -160 -> 114
    //   277: astore 9
    //   279: aload 6
    //   281: astore 15
    //   283: aload 5
    //   285: astore 11
    //   287: aconst_null
    //   288: astore 12
    //   290: aconst_null
    //   291: astore 14
    //   293: goto -179 -> 114
    //   296: astore 9
    //   298: aload 5
    //   300: astore 11
    //   302: aconst_null
    //   303: astore 12
    //   305: aload 6
    //   307: astore 24
    //   309: aload 7
    //   311: astore 14
    //   313: aload 24
    //   315: astore 15
    //   317: goto -203 -> 114
    //
    // Exception table:
    //   from	to	target	type
    //   62	85	88	finally
    //   157	162	88	finally
    //   167	172	204	java/io/IOException
    //   177	182	209	java/io/IOException
    //   187	192	214	java/io/IOException
    //   198	203	219	java/io/IOException
    //   119	124	222	java/io/IOException
    //   129	134	227	java/io/IOException
    //   139	144	232	java/io/IOException
    //   149	154	237	java/io/IOException
    //   2	30	242	finally
    //   30	41	259	finally
    //   41	51	277	finally
    //   51	62	296	finally
  }
}

/* Location:           F:\soft\android\soft\dex2jar-0.0.7.10-SNAPSHOT\classes.dex.dex2jar.jar
 * Qualified Name:     gl
 * JD-Core Version:    0.6.0
 */