package com.mobclick.android;

import android.content.Context;

final class i extends Thread
{
  private static final Object a = new Object();
  private Context b;
  private int c;
  private String d;
  private String e;
  private String f;
  private String g;
  private int h;

  i(Context paramContext, int paramInt)
  {
    this.b = paramContext;
    this.c = paramInt;
  }

  i(Context paramContext, String paramString, int paramInt)
  {
    this.b = paramContext;
    this.c = paramInt;
    this.d = paramString;
  }

  i(Context paramContext, String paramString1, String paramString2, int paramInt)
  {
    this.b = paramContext;
    this.c = paramInt;
    this.d = paramString1;
    this.e = paramString2;
  }

  i(Context paramContext, String paramString1, String paramString2, String paramString3, int paramInt1, int paramInt2)
  {
    this.b = paramContext;
    this.d = paramString1;
    this.f = paramString2;
    this.g = paramString3;
    this.h = paramInt1;
    this.c = paramInt2;
  }

  // ERROR //
  public void run()
  {
    // Byte code:
    //   0: getstatic 25	com/mobclick/android/i:a	Ljava/lang/Object;
    //   3: astore_1
    //   4: aload_1
    //   5: monitorenter
    //   6: aload_0
    //   7: getfield 31	com/mobclick/android/i:c	I
    //   10: istore_2
    //   11: iload_2
    //   12: ifne +75 -> 87
    //   15: aload_0
    //   16: getfield 29	com/mobclick/android/i:b	Landroid/content/Context;
    //   19: ifnonnull +14 -> 33
    //   22: ldc 49
    //   24: ldc 51
    //   26: invokestatic 56	android/util/Log:e	(Ljava/lang/String;Ljava/lang/String;)I
    //   29: istore_3
    //   30: aload_1
    //   31: monitorexit
    //   32: return
    //   33: invokestatic 61	com/mobclick/android/MobclickAgent:a	()Lcom/mobclick/android/MobclickAgent;
    //   36: astore 4
    //   38: aload_0
    //   39: getfield 29	com/mobclick/android/i:b	Landroid/content/Context;
    //   42: astore 5
    //   44: aload 4
    //   46: aload 5
    //   48: invokestatic 64	com/mobclick/android/MobclickAgent:a	(Lcom/mobclick/android/MobclickAgent;Landroid/content/Context;)V
    //   51: aload_1
    //   52: monitorexit
    //   53: return
    //   54: astore 6
    //   56: aload_1
    //   57: monitorexit
    //   58: aload 6
    //   60: athrow
    //   61: astore 7
    //   63: ldc 49
    //   65: ldc 66
    //   67: invokestatic 56	android/util/Log:e	(Ljava/lang/String;Ljava/lang/String;)I
    //   70: istore 8
    //   72: return
    //   73: astore 9
    //   75: ldc 49
    //   77: ldc 68
    //   79: invokestatic 56	android/util/Log:e	(Ljava/lang/String;Ljava/lang/String;)I
    //   82: istore 10
    //   84: goto -33 -> 51
    //   87: aload_0
    //   88: getfield 31	com/mobclick/android/i:c	I
    //   91: iconst_1
    //   92: if_icmpne +40 -> 132
    //   95: invokestatic 61	com/mobclick/android/MobclickAgent:a	()Lcom/mobclick/android/MobclickAgent;
    //   98: astore 11
    //   100: aload_0
    //   101: getfield 29	com/mobclick/android/i:b	Landroid/content/Context;
    //   104: astore 12
    //   106: aload_0
    //   107: getfield 34	com/mobclick/android/i:d	Ljava/lang/String;
    //   110: astore 13
    //   112: aload_0
    //   113: getfield 37	com/mobclick/android/i:e	Ljava/lang/String;
    //   116: astore 14
    //   118: aload 11
    //   120: aload 12
    //   122: aload 13
    //   124: aload 14
    //   126: invokestatic 71	com/mobclick/android/MobclickAgent:a	(Lcom/mobclick/android/MobclickAgent;Landroid/content/Context;Ljava/lang/String;Ljava/lang/String;)V
    //   129: goto -78 -> 51
    //   132: aload_0
    //   133: getfield 31	com/mobclick/android/i:c	I
    //   136: iconst_2
    //   137: if_icmpne +32 -> 169
    //   140: invokestatic 61	com/mobclick/android/MobclickAgent:a	()Lcom/mobclick/android/MobclickAgent;
    //   143: astore 15
    //   145: aload_0
    //   146: getfield 29	com/mobclick/android/i:b	Landroid/content/Context;
    //   149: astore 16
    //   151: aload_0
    //   152: getfield 34	com/mobclick/android/i:d	Ljava/lang/String;
    //   155: astore 17
    //   157: aload 15
    //   159: aload 16
    //   161: aload 17
    //   163: invokestatic 74	com/mobclick/android/MobclickAgent:a	(Lcom/mobclick/android/MobclickAgent;Landroid/content/Context;Ljava/lang/String;)V
    //   166: goto -115 -> 51
    //   169: aload_0
    //   170: getfield 31	com/mobclick/android/i:c	I
    //   173: iconst_3
    //   174: if_icmpne -123 -> 51
    //   177: invokestatic 61	com/mobclick/android/MobclickAgent:a	()Lcom/mobclick/android/MobclickAgent;
    //   180: astore 18
    //   182: aload_0
    //   183: getfield 29	com/mobclick/android/i:b	Landroid/content/Context;
    //   186: astore 19
    //   188: aload_0
    //   189: getfield 34	com/mobclick/android/i:d	Ljava/lang/String;
    //   192: astore 20
    //   194: aload_0
    //   195: getfield 40	com/mobclick/android/i:f	Ljava/lang/String;
    //   198: astore 21
    //   200: aload_0
    //   201: getfield 42	com/mobclick/android/i:g	Ljava/lang/String;
    //   204: astore 22
    //   206: aload_0
    //   207: getfield 44	com/mobclick/android/i:h	I
    //   210: istore 23
    //   212: aload 18
    //   214: aload 19
    //   216: aload 20
    //   218: aload 21
    //   220: aload 22
    //   222: iload 23
    //   224: invokestatic 77	com/mobclick/android/MobclickAgent:a	(Lcom/mobclick/android/MobclickAgent;Landroid/content/Context;Ljava/lang/String;Ljava/lang/String;Ljava/lang/String;I)V
    //   227: goto -176 -> 51
    //
    // Exception table:
    //   from	to	target	type
    //   6	11	54	finally
    //   15	30	54	finally
    //   30	32	54	finally
    //   33	51	54	finally
    //   51	54	54	finally
    //   75	227	54	finally
    //   0	6	61	java/lang/Exception
    //   58	61	61	java/lang/Exception
    //   15	30	73	java/lang/Exception
    //   33	51	73	java/lang/Exception
  }
}

/* Location:           F:\soft\android\soft\dex2jar-0.0.7.10-SNAPSHOT\classes.dex.dex2jar.jar
 * Qualified Name:     com.mobclick.android.i
 * JD-Core Version:    0.6.0
 */