import android.database.sqlite.SQLiteDatabase;

public class by extends bt
{
  public static boolean b(SQLiteDatabase paramSQLiteDatabase)
  {
    by localby = new by();
    localby.a(paramSQLiteDatabase);
    return localby.a();
  }

  // ERROR //
  public boolean a()
  {
    // Byte code:
    //   0: ldc 20
    //   2: ldc 22
    //   4: invokestatic 27	gj:a	(Ljava/lang/String;Ljava/lang/String;)V
    //   7: new 29	java/lang/StringBuilder
    //   10: dup
    //   11: invokespecial 30	java/lang/StringBuilder:<init>	()V
    //   14: ldc 32
    //   16: invokevirtual 36	java/lang/StringBuilder:append	(Ljava/lang/String;)Ljava/lang/StringBuilder;
    //   19: astore_1
    //   20: getstatic 41	co:a	Ljava/lang/String;
    //   23: astore_2
    //   24: aload_1
    //   25: aload_2
    //   26: invokevirtual 36	java/lang/StringBuilder:append	(Ljava/lang/String;)Ljava/lang/StringBuilder;
    //   29: ldc 43
    //   31: invokevirtual 36	java/lang/StringBuilder:append	(Ljava/lang/String;)Ljava/lang/StringBuilder;
    //   34: astore_3
    //   35: getstatic 46	co:e	Ljava/lang/String;
    //   38: astore 4
    //   40: aload_3
    //   41: aload 4
    //   43: invokevirtual 36	java/lang/StringBuilder:append	(Ljava/lang/String;)Ljava/lang/StringBuilder;
    //   46: ldc 48
    //   48: invokevirtual 36	java/lang/StringBuilder:append	(Ljava/lang/String;)Ljava/lang/StringBuilder;
    //   51: astore 5
    //   53: getstatic 53	cw:a	I
    //   56: istore 6
    //   58: aload 5
    //   60: iload 6
    //   62: invokevirtual 56	java/lang/StringBuilder:append	(I)Ljava/lang/StringBuilder;
    //   65: invokevirtual 60	java/lang/StringBuilder:toString	()Ljava/lang/String;
    //   68: astore 7
    //   70: ldc2_w 61
    //   73: dstore 8
    //   75: aload_0
    //   76: getfield 65	by:a	Landroid/database/sqlite/SQLiteDatabase;
    //   79: aload 7
    //   81: aconst_null
    //   82: invokevirtual 71	android/database/sqlite/SQLiteDatabase:rawQuery	(Ljava/lang/String;[Ljava/lang/String;)Landroid/database/Cursor;
    //   85: astore 10
    //   87: aload 10
    //   89: astore 11
    //   91: aload 11
    //   93: invokeinterface 76 1 0
    //   98: ifeq +32 -> 130
    //   101: aload 11
    //   103: ldc 78
    //   105: invokeinterface 82 2 0
    //   110: istore 12
    //   112: aload 11
    //   114: iload 12
    //   116: invokeinterface 86 2 0
    //   121: dstore 10
    //   123: dload 10
    //   125: dstore 8
    //   127: goto -36 -> 91
    //   130: aload 11
    //   132: invokeinterface 89 1 0
    //   137: new 29	java/lang/StringBuilder
    //   140: dup
    //   141: invokespecial 30	java/lang/StringBuilder:<init>	()V
    //   144: ldc 91
    //   146: invokevirtual 36	java/lang/StringBuilder:append	(Ljava/lang/String;)Ljava/lang/StringBuilder;
    //   149: astore 13
    //   151: getstatic 46	co:e	Ljava/lang/String;
    //   154: astore 14
    //   156: aload 13
    //   158: aload 14
    //   160: invokevirtual 36	java/lang/StringBuilder:append	(Ljava/lang/String;)Ljava/lang/StringBuilder;
    //   163: ldc 93
    //   165: invokevirtual 36	java/lang/StringBuilder:append	(Ljava/lang/String;)Ljava/lang/StringBuilder;
    //   168: astore 15
    //   170: getstatic 53	cw:a	I
    //   173: istore 16
    //   175: aload 15
    //   177: iload 16
    //   179: invokevirtual 56	java/lang/StringBuilder:append	(I)Ljava/lang/StringBuilder;
    //   182: invokevirtual 60	java/lang/StringBuilder:toString	()Ljava/lang/String;
    //   185: astore 17
    //   187: aload_0
    //   188: getfield 65	by:a	Landroid/database/sqlite/SQLiteDatabase;
    //   191: aload 17
    //   193: aconst_null
    //   194: invokevirtual 71	android/database/sqlite/SQLiteDatabase:rawQuery	(Ljava/lang/String;[Ljava/lang/String;)Landroid/database/Cursor;
    //   197: astore 18
    //   199: aload 18
    //   201: astore 19
    //   203: ldc 95
    //   205: invokestatic 101	java/lang/Long:valueOf	(Ljava/lang/String;)Ljava/lang/Long;
    //   208: invokevirtual 105	java/lang/Long:longValue	()J
    //   211: lstore 20
    //   213: aload 19
    //   215: invokeinterface 76 1 0
    //   220: ifeq +155 -> 375
    //   223: new 107	android/content/ContentValues
    //   226: dup
    //   227: invokespecial 108	android/content/ContentValues:<init>	()V
    //   230: astore 22
    //   232: getstatic 111	co:d	Ljava/lang/String;
    //   235: astore 23
    //   237: dload 8
    //   239: invokestatic 116	java/lang/Double:valueOf	(D)Ljava/lang/Double;
    //   242: astore 24
    //   244: aload 22
    //   246: aload 23
    //   248: aload 24
    //   250: invokevirtual 120	android/content/ContentValues:put	(Ljava/lang/String;Ljava/lang/Double;)V
    //   253: getstatic 123	co:f	Ljava/lang/String;
    //   256: astore 25
    //   258: lload 20
    //   260: invokestatic 126	java/lang/Long:valueOf	(J)Ljava/lang/Long;
    //   263: astore 26
    //   265: aload 22
    //   267: aload 25
    //   269: aload 26
    //   271: invokevirtual 129	android/content/ContentValues:put	(Ljava/lang/String;Ljava/lang/Long;)V
    //   274: new 29	java/lang/StringBuilder
    //   277: dup
    //   278: invokespecial 30	java/lang/StringBuilder:<init>	()V
    //   281: astore 27
    //   283: getstatic 46	co:e	Ljava/lang/String;
    //   286: astore 28
    //   288: aload 27
    //   290: aload 28
    //   292: invokevirtual 36	java/lang/StringBuilder:append	(Ljava/lang/String;)Ljava/lang/StringBuilder;
    //   295: ldc 131
    //   297: invokevirtual 36	java/lang/StringBuilder:append	(Ljava/lang/String;)Ljava/lang/StringBuilder;
    //   300: invokevirtual 60	java/lang/StringBuilder:toString	()Ljava/lang/String;
    //   303: astore 29
    //   305: iconst_1
    //   306: anewarray 133	java/lang/String
    //   309: astore 30
    //   311: getstatic 53	cw:a	I
    //   314: invokestatic 136	java/lang/String:valueOf	(I)Ljava/lang/String;
    //   317: astore 31
    //   319: aload 30
    //   321: iconst_0
    //   322: aload 31
    //   324: aastore
    //   325: aload_0
    //   326: getfield 65	by:a	Landroid/database/sqlite/SQLiteDatabase;
    //   329: astore 32
    //   331: getstatic 41	co:a	Ljava/lang/String;
    //   334: astore 33
    //   336: aload 32
    //   338: aload 33
    //   340: aload 22
    //   342: aload 29
    //   344: aload 30
    //   346: invokevirtual 140	android/database/sqlite/SQLiteDatabase:update	(Ljava/lang/String;Landroid/content/ContentValues;Ljava/lang/String;[Ljava/lang/String;)I
    //   349: istore 34
    //   351: aload 19
    //   353: invokeinterface 89 1 0
    //   358: iconst_1
    //   359: ireturn
    //   360: astore 35
    //   362: aconst_null
    //   363: astore 36
    //   365: aload 36
    //   367: invokeinterface 89 1 0
    //   372: aload 35
    //   374: athrow
    //   375: new 29	java/lang/StringBuilder
    //   378: dup
    //   379: invokespecial 30	java/lang/StringBuilder:<init>	()V
    //   382: ldc 142
    //   384: invokevirtual 36	java/lang/StringBuilder:append	(Ljava/lang/String;)Ljava/lang/StringBuilder;
    //   387: dload 8
    //   389: invokevirtual 145	java/lang/StringBuilder:append	(D)Ljava/lang/StringBuilder;
    //   392: ldc 147
    //   394: invokevirtual 36	java/lang/StringBuilder:append	(Ljava/lang/String;)Ljava/lang/StringBuilder;
    //   397: lload 20
    //   399: invokevirtual 150	java/lang/StringBuilder:append	(J)Ljava/lang/StringBuilder;
    //   402: ldc 152
    //   404: invokevirtual 36	java/lang/StringBuilder:append	(Ljava/lang/String;)Ljava/lang/StringBuilder;
    //   407: invokevirtual 60	java/lang/StringBuilder:toString	()Ljava/lang/String;
    //   410: astore 37
    //   412: aload_0
    //   413: getfield 65	by:a	Landroid/database/sqlite/SQLiteDatabase;
    //   416: aload 37
    //   418: invokevirtual 156	android/database/sqlite/SQLiteDatabase:execSQL	(Ljava/lang/String;)V
    //   421: goto -70 -> 351
    //   424: astore 38
    //   426: aload 19
    //   428: astore 39
    //   430: aload 38
    //   432: astore 40
    //   434: aload 39
    //   436: invokeinterface 89 1 0
    //   441: aload 40
    //   443: athrow
    //   444: astore 40
    //   446: aconst_null
    //   447: astore 39
    //   449: goto -15 -> 434
    //   452: astore 41
    //   454: aload 11
    //   456: astore 36
    //   458: aload 41
    //   460: astore 35
    //   462: goto -97 -> 365
    //
    // Exception table:
    //   from	to	target	type
    //   75	87	360	finally
    //   203	351	424	finally
    //   375	421	424	finally
    //   187	199	444	finally
    //   91	123	452	finally
  }
}

/* Location:           F:\soft\android\soft\dex2jar-0.0.7.10-SNAPSHOT\classes.dex.dex2jar.jar
 * Qualified Name:     by
 * JD-Core Version:    0.6.0
 */