import java.net.URL;
import java.util.Map;
import java.util.concurrent.Callable;

class go
  implements Callable
{
  URL a;
  Map b;
  Map c;

  public go(URL paramURL, Map paramMap1, Map paramMap2)
  {
    this.a = paramURL;
    this.b = paramMap1;
    this.c = paramMap2;
  }

  // ERROR //
  public Map a()
  {
    // Byte code:
    //   0: new 27	java/util/HashMap
    //   3: dup
    //   4: invokespecial 28	java/util/HashMap:<init>	()V
    //   7: astore_1
    //   8: iconst_0
    //   9: istore_2
    //   10: aload_0
    //   11: getfield 18	go:a	Ljava/net/URL;
    //   14: invokevirtual 34	java/net/URL:getProtocol	()Ljava/lang/String;
    //   17: astore_3
    //   18: aload_0
    //   19: getfield 18	go:a	Ljava/net/URL;
    //   22: invokevirtual 37	java/net/URL:getHost	()Ljava/lang/String;
    //   25: astore 4
    //   27: aload_0
    //   28: getfield 18	go:a	Ljava/net/URL;
    //   31: invokevirtual 41	java/net/URL:getPort	()I
    //   34: istore 5
    //   36: new 43	java/lang/StringBuilder
    //   39: dup
    //   40: invokespecial 44	java/lang/StringBuilder:<init>	()V
    //   43: astore 6
    //   45: aload_0
    //   46: getfield 18	go:a	Ljava/net/URL;
    //   49: invokevirtual 47	java/net/URL:getPath	()Ljava/lang/String;
    //   52: astore 7
    //   54: aload 6
    //   56: aload 7
    //   58: invokevirtual 51	java/lang/StringBuilder:append	(Ljava/lang/String;)Ljava/lang/StringBuilder;
    //   61: ldc 53
    //   63: invokevirtual 51	java/lang/StringBuilder:append	(Ljava/lang/String;)Ljava/lang/StringBuilder;
    //   66: invokevirtual 56	java/lang/StringBuilder:toString	()Ljava/lang/String;
    //   69: astore 8
    //   71: new 30	java/net/URL
    //   74: dup
    //   75: aload_3
    //   76: aload 4
    //   78: iload 5
    //   80: aload 8
    //   82: invokespecial 59	java/net/URL:<init>	(Ljava/lang/String;Ljava/lang/String;ILjava/lang/String;)V
    //   85: invokevirtual 63	java/net/URL:openConnection	()Ljava/net/URLConnection;
    //   88: checkcast 65	java/net/HttpURLConnection
    //   91: astore 9
    //   93: getstatic 70	gn:c	I
    //   96: istore 10
    //   98: aload 9
    //   100: iload 10
    //   102: invokevirtual 74	java/net/HttpURLConnection:setConnectTimeout	(I)V
    //   105: aload 9
    //   107: sipush 30000
    //   110: invokevirtual 77	java/net/HttpURLConnection:setReadTimeout	(I)V
    //   113: aload 9
    //   115: ldc 79
    //   117: invokevirtual 83	java/net/HttpURLConnection:setRequestMethod	(Ljava/lang/String;)V
    //   120: aload 9
    //   122: ldc 84
    //   124: invokevirtual 88	java/net/HttpURLConnection:setDoInput	(Z)V
    //   127: aload 9
    //   129: ldc 84
    //   131: invokevirtual 91	java/net/HttpURLConnection:setDoOutput	(Z)V
    //   134: aload 9
    //   136: ldc 92
    //   138: invokevirtual 95	java/net/HttpURLConnection:setUseCaches	(Z)V
    //   141: invokestatic 101	java/util/UUID:randomUUID	()Ljava/util/UUID;
    //   144: invokevirtual 102	java/util/UUID:toString	()Ljava/lang/String;
    //   147: astore 11
    //   149: aload 9
    //   151: ldc 104
    //   153: ldc 106
    //   155: invokevirtual 110	java/net/HttpURLConnection:setRequestProperty	(Ljava/lang/String;Ljava/lang/String;)V
    //   158: aload 9
    //   160: ldc 112
    //   162: ldc 114
    //   164: invokevirtual 110	java/net/HttpURLConnection:setRequestProperty	(Ljava/lang/String;Ljava/lang/String;)V
    //   167: aload 9
    //   169: ldc 116
    //   171: ldc 118
    //   173: invokevirtual 110	java/net/HttpURLConnection:setRequestProperty	(Ljava/lang/String;Ljava/lang/String;)V
    //   176: aload 9
    //   178: ldc 120
    //   180: ldc 122
    //   182: invokevirtual 110	java/net/HttpURLConnection:setRequestProperty	(Ljava/lang/String;Ljava/lang/String;)V
    //   185: aload 9
    //   187: ldc 124
    //   189: ldc 126
    //   191: invokevirtual 110	java/net/HttpURLConnection:setRequestProperty	(Ljava/lang/String;Ljava/lang/String;)V
    //   194: new 43	java/lang/StringBuilder
    //   197: dup
    //   198: invokespecial 44	java/lang/StringBuilder:<init>	()V
    //   201: ldc 128
    //   203: invokevirtual 51	java/lang/StringBuilder:append	(Ljava/lang/String;)Ljava/lang/StringBuilder;
    //   206: aload 11
    //   208: invokevirtual 51	java/lang/StringBuilder:append	(Ljava/lang/String;)Ljava/lang/StringBuilder;
    //   211: invokevirtual 56	java/lang/StringBuilder:toString	()Ljava/lang/String;
    //   214: astore 12
    //   216: aload 9
    //   218: ldc 130
    //   220: aload 12
    //   222: invokevirtual 110	java/net/HttpURLConnection:setRequestProperty	(Ljava/lang/String;Ljava/lang/String;)V
    //   225: aload_0
    //   226: getfield 22	go:c	Ljava/util/Map;
    //   229: ifnull +112 -> 341
    //   232: aload_0
    //   233: getfield 22	go:c	Ljava/util/Map;
    //   236: invokeinterface 136 1 0
    //   241: invokeinterface 142 1 0
    //   246: astore 13
    //   248: aload 13
    //   250: invokeinterface 148 1 0
    //   255: ifeq +86 -> 341
    //   258: aload 13
    //   260: invokeinterface 152 1 0
    //   265: checkcast 154	java/util/Map$Entry
    //   268: astore 14
    //   270: aload 14
    //   272: invokeinterface 157 1 0
    //   277: checkcast 159	java/lang/String
    //   280: astore 15
    //   282: aload 14
    //   284: invokeinterface 162 1 0
    //   289: checkcast 159	java/lang/String
    //   292: astore 16
    //   294: aload 9
    //   296: aload 15
    //   298: aload 16
    //   300: invokevirtual 110	java/net/HttpURLConnection:setRequestProperty	(Ljava/lang/String;Ljava/lang/String;)V
    //   303: goto -55 -> 248
    //   306: astore 17
    //   308: new 164	ef
    //   311: dup
    //   312: ldc 166
    //   314: invokespecial 168	ef:<init>	(Ljava/lang/String;)V
    //   317: athrow
    //   318: astore 18
    //   320: aload 9
    //   322: astore 19
    //   324: aload 18
    //   326: astore 20
    //   328: aload 19
    //   330: ifnull +8 -> 338
    //   333: aload 19
    //   335: invokevirtual 171	java/net/HttpURLConnection:disconnect	()V
    //   338: aload 20
    //   340: athrow
    //   341: sipush 25000
    //   344: istore_2
    //   345: aload 9
    //   347: iload_2
    //   348: invokevirtual 77	java/net/HttpURLConnection:setReadTimeout	(I)V
    //   351: getstatic 174	gn:a	Ljava/lang/String;
    //   354: ldc 176
    //   356: invokestatic 180	gj:a	(Ljava/lang/String;Ljava/lang/String;)V
    //   359: aload 9
    //   361: invokevirtual 184	java/net/HttpURLConnection:getOutputStream	()Ljava/io/OutputStream;
    //   364: astore 21
    //   366: new 186	java/io/DataOutputStream
    //   369: dup
    //   370: aload 21
    //   372: invokespecial 189	java/io/DataOutputStream:<init>	(Ljava/io/OutputStream;)V
    //   375: astore 22
    //   377: getstatic 174	gn:a	Ljava/lang/String;
    //   380: ldc 191
    //   382: invokestatic 180	gj:a	(Ljava/lang/String;Ljava/lang/String;)V
    //   385: getstatic 194	gn:d	I
    //   388: istore 13
    //   390: aload_0
    //   391: getfield 20	go:b	Ljava/util/Map;
    //   394: ifnull +361 -> 755
    //   397: aload_0
    //   398: getfield 20	go:b	Ljava/util/Map;
    //   401: invokeinterface 136 1 0
    //   406: invokeinterface 142 1 0
    //   411: astore 23
    //   413: aload 23
    //   415: invokeinterface 148 1 0
    //   420: ifeq +335 -> 755
    //   423: aload 23
    //   425: invokeinterface 152 1 0
    //   430: checkcast 154	java/util/Map$Entry
    //   433: astore 24
    //   435: new 43	java/lang/StringBuilder
    //   438: dup
    //   439: invokespecial 44	java/lang/StringBuilder:<init>	()V
    //   442: astore 25
    //   444: getstatic 197	gn:e	Ljava/lang/String;
    //   447: astore 26
    //   449: aload 25
    //   451: aload 26
    //   453: invokevirtual 51	java/lang/StringBuilder:append	(Ljava/lang/String;)Ljava/lang/StringBuilder;
    //   456: aload 11
    //   458: invokevirtual 51	java/lang/StringBuilder:append	(Ljava/lang/String;)Ljava/lang/StringBuilder;
    //   461: invokevirtual 56	java/lang/StringBuilder:toString	()Ljava/lang/String;
    //   464: astore 27
    //   466: aload 22
    //   468: aload 27
    //   470: invokevirtual 200	java/io/DataOutputStream:writeBytes	(Ljava/lang/String;)V
    //   473: aload 24
    //   475: invokeinterface 162 1 0
    //   480: checkcast 202	java/io/File
    //   483: astore 28
    //   485: new 204	java/io/FileInputStream
    //   488: dup
    //   489: aload 28
    //   491: invokespecial 207	java/io/FileInputStream:<init>	(Ljava/io/File;)V
    //   494: astore 29
    //   496: aload 29
    //   498: invokevirtual 210	java/io/FileInputStream:available	()I
    //   501: iload 13
    //   503: invokestatic 216	java/lang/Math:min	(II)I
    //   506: istore 30
    //   508: iload 30
    //   510: newarray byte
    //   512: astore 31
    //   514: aload 29
    //   516: aload 31
    //   518: iconst_0
    //   519: iload 30
    //   521: invokevirtual 220	java/io/FileInputStream:read	([BII)I
    //   524: istore 32
    //   526: aload 24
    //   528: invokeinterface 162 1 0
    //   533: checkcast 202	java/io/File
    //   536: invokevirtual 223	java/io/File:getName	()Ljava/lang/String;
    //   539: astore 33
    //   541: getstatic 226	gn:f	Ljava/lang/String;
    //   544: astore 34
    //   546: aload 22
    //   548: aload 34
    //   550: invokevirtual 200	java/io/DataOutputStream:writeBytes	(Ljava/lang/String;)V
    //   553: new 43	java/lang/StringBuilder
    //   556: dup
    //   557: invokespecial 44	java/lang/StringBuilder:<init>	()V
    //   560: ldc 228
    //   562: invokevirtual 51	java/lang/StringBuilder:append	(Ljava/lang/String;)Ljava/lang/StringBuilder;
    //   565: astore 35
    //   567: aload 24
    //   569: invokeinterface 157 1 0
    //   574: checkcast 159	java/lang/String
    //   577: astore 36
    //   579: aload 35
    //   581: aload 36
    //   583: invokevirtual 51	java/lang/StringBuilder:append	(Ljava/lang/String;)Ljava/lang/StringBuilder;
    //   586: ldc 230
    //   588: invokevirtual 51	java/lang/StringBuilder:append	(Ljava/lang/String;)Ljava/lang/StringBuilder;
    //   591: ldc 232
    //   593: invokevirtual 51	java/lang/StringBuilder:append	(Ljava/lang/String;)Ljava/lang/StringBuilder;
    //   596: aload 33
    //   598: invokevirtual 51	java/lang/StringBuilder:append	(Ljava/lang/String;)Ljava/lang/StringBuilder;
    //   601: invokevirtual 56	java/lang/StringBuilder:toString	()Ljava/lang/String;
    //   604: astore 37
    //   606: aload 22
    //   608: aload 37
    //   610: invokevirtual 200	java/io/DataOutputStream:writeBytes	(Ljava/lang/String;)V
    //   613: new 43	java/lang/StringBuilder
    //   616: dup
    //   617: invokespecial 44	java/lang/StringBuilder:<init>	()V
    //   620: ldc 234
    //   622: invokevirtual 51	java/lang/StringBuilder:append	(Ljava/lang/String;)Ljava/lang/StringBuilder;
    //   625: astore 38
    //   627: getstatic 226	gn:f	Ljava/lang/String;
    //   630: astore 39
    //   632: aload 38
    //   634: aload 39
    //   636: invokevirtual 51	java/lang/StringBuilder:append	(Ljava/lang/String;)Ljava/lang/StringBuilder;
    //   639: invokevirtual 56	java/lang/StringBuilder:toString	()Ljava/lang/String;
    //   642: astore 40
    //   644: aload 22
    //   646: aload 40
    //   648: invokevirtual 200	java/io/DataOutputStream:writeBytes	(Ljava/lang/String;)V
    //   651: new 43	java/lang/StringBuilder
    //   654: dup
    //   655: invokespecial 44	java/lang/StringBuilder:<init>	()V
    //   658: ldc 236
    //   660: invokevirtual 51	java/lang/StringBuilder:append	(Ljava/lang/String;)Ljava/lang/StringBuilder;
    //   663: astore 41
    //   665: getstatic 226	gn:f	Ljava/lang/String;
    //   668: astore 42
    //   670: aload 41
    //   672: aload 42
    //   674: invokevirtual 51	java/lang/StringBuilder:append	(Ljava/lang/String;)Ljava/lang/StringBuilder;
    //   677: invokevirtual 56	java/lang/StringBuilder:toString	()Ljava/lang/String;
    //   680: astore 43
    //   682: aload 22
    //   684: aload 43
    //   686: invokevirtual 200	java/io/DataOutputStream:writeBytes	(Ljava/lang/String;)V
    //   689: getstatic 226	gn:f	Ljava/lang/String;
    //   692: astore 44
    //   694: aload 22
    //   696: aload 44
    //   698: invokevirtual 200	java/io/DataOutputStream:writeBytes	(Ljava/lang/String;)V
    //   701: iload 30
    //   703: istore_2
    //   704: iload 32
    //   706: istore 45
    //   708: iload 45
    //   710: ifle +37 -> 747
    //   713: aload 22
    //   715: aload 31
    //   717: iconst_0
    //   718: iload_2
    //   719: invokevirtual 240	java/io/DataOutputStream:write	([BII)V
    //   722: aload 29
    //   724: invokevirtual 210	java/io/FileInputStream:available	()I
    //   727: iload 13
    //   729: invokestatic 216	java/lang/Math:min	(II)I
    //   732: istore_2
    //   733: aload 29
    //   735: aload 31
    //   737: iconst_0
    //   738: iload_2
    //   739: invokevirtual 220	java/io/FileInputStream:read	([BII)I
    //   742: istore 45
    //   744: goto -36 -> 708
    //   747: aload 29
    //   749: invokevirtual 243	java/io/FileInputStream:close	()V
    //   752: goto -339 -> 413
    //   755: getstatic 226	gn:f	Ljava/lang/String;
    //   758: astore 46
    //   760: aload 22
    //   762: aload 46
    //   764: invokevirtual 200	java/io/DataOutputStream:writeBytes	(Ljava/lang/String;)V
    //   767: new 43	java/lang/StringBuilder
    //   770: dup
    //   771: invokespecial 44	java/lang/StringBuilder:<init>	()V
    //   774: astore 47
    //   776: getstatic 197	gn:e	Ljava/lang/String;
    //   779: astore 48
    //   781: aload 47
    //   783: aload 48
    //   785: invokevirtual 51	java/lang/StringBuilder:append	(Ljava/lang/String;)Ljava/lang/StringBuilder;
    //   788: aload 11
    //   790: invokevirtual 51	java/lang/StringBuilder:append	(Ljava/lang/String;)Ljava/lang/StringBuilder;
    //   793: astore 49
    //   795: getstatic 197	gn:e	Ljava/lang/String;
    //   798: astore 50
    //   800: aload 49
    //   802: aload 50
    //   804: invokevirtual 51	java/lang/StringBuilder:append	(Ljava/lang/String;)Ljava/lang/StringBuilder;
    //   807: invokevirtual 56	java/lang/StringBuilder:toString	()Ljava/lang/String;
    //   810: astore 51
    //   812: aload 22
    //   814: aload 51
    //   816: invokevirtual 200	java/io/DataOutputStream:writeBytes	(Ljava/lang/String;)V
    //   819: getstatic 226	gn:f	Ljava/lang/String;
    //   822: astore 52
    //   824: aload 22
    //   826: aload 52
    //   828: invokevirtual 200	java/io/DataOutputStream:writeBytes	(Ljava/lang/String;)V
    //   831: aload 22
    //   833: invokevirtual 246	java/io/DataOutputStream:size	()I
    //   836: istore 53
    //   838: aload 22
    //   840: invokevirtual 249	java/io/DataOutputStream:flush	()V
    //   843: aload 22
    //   845: invokevirtual 250	java/io/DataOutputStream:close	()V
    //   848: aload 9
    //   850: invokevirtual 253	java/net/HttpURLConnection:getResponseCode	()I
    //   853: istore_2
    //   854: iload_2
    //   855: sipush 200
    //   858: if_icmpeq +10 -> 868
    //   861: iload_2
    //   862: sipush 204
    //   865: if_icmpne +97 -> 962
    //   868: aload 9
    //   870: ldc 255
    //   872: invokevirtual 259	java/net/HttpURLConnection:getHeaderField	(Ljava/lang/String;)Ljava/lang/String;
    //   875: invokestatic 264	gx:a	(Ljava/lang/Object;)Ljava/lang/String;
    //   878: astore 54
    //   880: aload_1
    //   881: ldc 255
    //   883: aload 54
    //   885: invokeinterface 268 3 0
    //   890: astore 55
    //   892: aload 9
    //   894: ldc_w 270
    //   897: invokevirtual 259	java/net/HttpURLConnection:getHeaderField	(Ljava/lang/String;)Ljava/lang/String;
    //   900: invokestatic 264	gx:a	(Ljava/lang/Object;)Ljava/lang/String;
    //   903: astore 56
    //   905: aload_1
    //   906: ldc_w 270
    //   909: aload 56
    //   911: invokeinterface 268 3 0
    //   916: astore 57
    //   918: aload 9
    //   920: ldc_w 272
    //   923: invokevirtual 259	java/net/HttpURLConnection:getHeaderField	(Ljava/lang/String;)Ljava/lang/String;
    //   926: invokestatic 264	gx:a	(Ljava/lang/Object;)Ljava/lang/String;
    //   929: ldc_w 274
    //   932: invokestatic 280	java/net/URLDecoder:decode	(Ljava/lang/String;Ljava/lang/String;)Ljava/lang/String;
    //   935: astore 58
    //   937: aload_1
    //   938: ldc_w 272
    //   941: aload 58
    //   943: invokeinterface 268 3 0
    //   948: astore 59
    //   950: aload 9
    //   952: ifnull +8 -> 960
    //   955: aload 9
    //   957: invokevirtual 171	java/net/HttpURLConnection:disconnect	()V
    //   960: aload_1
    //   961: areturn
    //   962: new 43	java/lang/StringBuilder
    //   965: dup
    //   966: invokespecial 44	java/lang/StringBuilder:<init>	()V
    //   969: ldc_w 282
    //   972: invokevirtual 51	java/lang/StringBuilder:append	(Ljava/lang/String;)Ljava/lang/StringBuilder;
    //   975: iload_2
    //   976: invokevirtual 285	java/lang/StringBuilder:append	(I)Ljava/lang/StringBuilder;
    //   979: invokevirtual 56	java/lang/StringBuilder:toString	()Ljava/lang/String;
    //   982: astore 60
    //   984: new 287	ej
    //   987: dup
    //   988: aload 60
    //   990: invokespecial 288	ej:<init>	(Ljava/lang/String;)V
    //   993: athrow
    //   994: astore 20
    //   996: goto -668 -> 328
    //   999: astore 61
    //   1001: aconst_null
    //   1002: astore 9
    //   1004: goto -696 -> 308
    //
    // Exception table:
    //   from	to	target	type
    //   93	303	306	java/lang/Exception
    //   345	950	306	java/lang/Exception
    //   962	994	306	java/lang/Exception
    //   93	303	318	finally
    //   308	318	318	finally
    //   345	950	318	finally
    //   962	994	318	finally
    //   10	93	994	finally
    //   10	93	999	java/lang/Exception
  }
}

/* Location:           F:\soft\android\soft\dex2jar-0.0.7.10-SNAPSHOT\classes.dex.dex2jar.jar
 * Qualified Name:     go
 * JD-Core Version:    0.6.0
 */